Workbook

Sheet INVOICE
A1: INVOICE
G5: インボイス作成日（Date): 5/12/2025
A8: 依頼住 (Shipper Address) | G8: Invoice No MASUDA VN-JP 019/25
A10: MASUDA VINYL VIETNAM CO.,LTD
A11: LOT NO1 DONG VANG DINH TRAM INDUSTRIAL ZONE | G11: (原産国) Country of Origin | I11: (仕向先国名) Country of Destination
A12: NENH WARD BAC NINH PROVINCE
A13: TEL : 0204 3662 777 | G13: VIETNAM | I13: JAPAN
A14: FAX : 0204 3662 825 | G14: 支払条件 (Terms of Payment)
G15: 20日締め翌月末支払 (Invoice will be closed on 20th every month and payment at end of the following month)
A16: 荷受人(Consigneer)
A19: MASUDA VINYL CO.,LTD
A20: 390ROKUGAIKECYOU KITAKU | G20: 備考 (Remark):
A21: NAGOYA CITY AICHI JAPAN
A22: TEL : 052-901-9373 | G22: P | H22: 有償（Commerical Value)
A23: FAX : 052-901-6943 | H23: 無償（No Commerical Value)
A25: Delivery to (着地) | F25: CIF | H25: 贈物（Gift)
H26: 商品見本（ Sample, No Commercial Value )
H27: その他（Other)
A30: ラベル内容 (Marks & Nos.) | B30: 内容品の記載 (Description) | D30: 注文書No PO No | E30: 単位 （Unit） | F30: 数量 （Quantity) | G30: 単価 （Unit Price） | I30: 合計 （Total Amount)
A33: 1/13 | B33: TABLE EDGE MG23 | E33: =VLOOKUP(B33,データ!$B$3:$L$85,11,FALSE) -> m | F33: 4000 | G33: =VLOOKUP(B33,データ!$B$3:$C$85,2,FALSE) -> 0.61 | I33: =G33*F33 -> 2440
A34: 2/13 | B34: PUROTEKUTA 55788-16110 | E34: =VLOOKUP(B34,データ!$B$3:$L$85,11,FALSE) -> pcs | F34: 11000 | G34: =VLOOKUP(B34,データ!$B$3:$C$85,2,FALSE) -> 0.223 | I34: =G34*F34 -> 2453
A35: 3/13 | B35: PUROTEKUTA 55788-52350 | E35: =VLOOKUP(B35,データ!$B$3:$L$85,11,FALSE) -> pcs | F35: 6000 | G35: =VLOOKUP(B35,データ!$B$3:$C$85,2,FALSE) -> 0.213 | I35: =G35*F35 -> 1278
B36: PUROTEKUTA 55788-52360 | E36: =VLOOKUP(B36,データ!$B$3:$L$85,11,FALSE) -> pcs | F36: 5000 | G36: =VLOOKUP(B36,データ!$B$3:$C$85,2,FALSE) -> 0.223 | I36: =G36*F36 -> 1115
A37: 4/13 | B37: PUROTEKUTA 2A4P1-022G | E37: =VLOOKUP(B37,データ!$B$3:$L$85,11,FALSE) -> pcs | F37: 11000 | G37: =VLOOKUP(B37,データ!$B$3:$C$85,2,FALSE) -> 0.235 | I37: =G37*F37 -> 2585
B38: PUROTEKUTA 55788-K0060 | E38: =VLOOKUP(B38,データ!$B$3:$L$85,11,FALSE) -> pcs | F38: 5500 | G38: =VLOOKUP(B38,データ!$B$3:$C$85,2,FALSE) -> 0.224 | I38: =G38*F38 -> 1232
A39: 5/13 | B39: PUROTEKUTA 55788-48090 | E39: =VLOOKUP(B39,データ!$B$3:$L$85,11,FALSE) -> pcs | F39: 9000 | G39: =VLOOKUP(B39,データ!$B$3:$C$85,2,FALSE) -> 0.251 | I39: =G39*F39 -> 2259
B40: PUROTEKUTA 55788-K0060 | E40: =VLOOKUP(B40,データ!$B$3:$L$85,11,FALSE) -> pcs | F40: 5500 | G40: =VLOOKUP(B40,データ!$B$3:$C$85,2,FALSE) -> 0.224 | I40: =G40*F40 -> 1232
A41: 6/13 | B41: PUROTEKUTA 55788-K0060 | E41: =VLOOKUP(B41,データ!$B$3:$L$85,11,FALSE) -> pcs | F41: 13500 | G41: =VLOOKUP(B41,データ!$B$3:$C$85,2,FALSE) -> 0.224 | I41: =G41*F41 -> 3024
A42: 7/13 | B42: PUROTEKUTA 55788-60110 | E42: =VLOOKUP(B42,データ!$B$3:$L$85,11,FALSE) -> pcs | F42: 13000 | G42: =VLOOKUP(B42,データ!$B$3:$C$85,2,FALSE) -> 0.223 | I42: =G42*F42 -> 2899
B43: RAB0938-V+H450 - N | E43: =VLOOKUP(B43,データ!$B$3:$DH$185,11,FALSE) -> pcs | F43: 7 | G43: =VLOOKUP(B43,データ!$B$3:$C$185,2,FALSE) -> 2.91 | I43: =G43*F43 -> 20.37
A44: 8/13-12/13 | B44: MASK 42811 | E44: =VLOOKUP(B44,データ!$B$3:$L$85,11,FALSE) -> bag | F44: 12000 | G44: =VLOOKUP(B44,データ!$B$3:$C$85,2,FALSE) -> 0.2 | I44: =G44*F44 -> 2400
A45: 13/13 | B45: TABLE EDGE MI3 156 | E45: =VLOOKUP(B45,データ!$B$3:$L$85,11,FALSE) -> pcs | F45: 240 | G45: =VLOOKUP(B45,データ!$B$3:$C$85,2,FALSE) -> 2.875 | I45: =G45*F45 -> 690
A46: 合計 （Total) | I46: =SUM(I33:K45) -> 23627.37
A49: 原産国 (Country of Origin) : VIETNAM | G49: 署名（ Singnature )
A50: CIF TO NAGOYA PORT

Sheet PACKING LIST
A1: PACKING LIST
H5: =INVOICE!G5 -> インボイス作成日（Date): 5/12/2025
A8: 依頼住 (Shipper Address) | H8: =INVOICE!G8 -> Invoice No MASUDA VN-JP 019/25
A10: MASUDA VINYL VIETNAM CO.,LTD
A11: LOT NO1 DONG VANG DINH TRAM INDUSTRIAL ZONE | H11: (原産国) Country of Origin | J11: (仕向先国名) Country of Destination
A12: NENH WARD BAC NINH PROVINCE
A13: TEL : 0204 3662 777 | H13: VIETNAM | J13: JAPAN
A14: FAX : 0204 3662 825 | H14: 支払条件 (Terms of Payment)
H15: 20日締め翌月末支払 (Invoice will be closed on 20th every month and payment at end of the following month)
A17: 荷受人(Consigneer)
A20: MASUDA VINYL CO.,LTD | H20: 備考 (Remark):
A21: 390ROKUGAIKECYOU KITAKU
A22: NAGOYA CITY AICHI JAPAN | H22: P | I22: 有償（Commerical Value)
A23: TEL : 052-901-9373 | I23: 無償（No Commerical Value)
A24: FAX : 052-901-6943
I25: 贈物（Gift)
A26: Delivery to (着地) | G26: CIF | I26: 商品見本（ Sample, No Commercial Value )
I27: その他（Other)
A31: ラベル内容 (Marks & Nos.) | B31: 内容品の記載 (Description) | D31: 注文書No PO No | E31: 単位 （Unit） | F31: 数量 （Quantity) | G31: 梱包 （Packing） | I31: 箱数 ( Number of Boxs) | J31: パレット数 ( Number of Pallets) | K31: 総重量 (Gross weight)
A35: 1/13 | B35: =INVOICE!B33 -> TABLE EDGE MG23 | E35: =INVOICE!E33 -> m | F35: =INVOICE!F33 -> 4000 | G35: =VLOOKUP(B35,データ!$B$3:$E$85,4,FALSE) -> 50 | I35: =ROUNDUP(F35/G35,0) -> 80 | J35: 1 | K35: =ROUND(N35+P35+20,2) -> 20
A36: 2/13 | B36: =INVOICE!B34 -> PUROTEKUTA 55788-16110 | E36: =INVOICE!E34 -> pcs | F36: =INVOICE!F34 -> 11000 | G36: =VLOOKUP(B36,データ!$B$3:$E$85,4,FALSE) -> 500 | I36: =ROUNDUP(F36/G36,0) -> 22 | J36: 1 | K36: =ROUND(N36+P36,2)+10 -> 10
A37: 3/13 | B37: =INVOICE!B35 -> PUROTEKUTA 55788-52350 | E37: =INVOICE!E35 -> pcs | F37: =INVOICE!F35 -> 6000 | G37: =VLOOKUP(B37,データ!$B$3:$E$85,4,FALSE) -> 500 | I37: =ROUNDUP(F37/G37,0) -> 12 | J37: 1 | K37: =ROUND(N37+P37,2)+5 -> 5
B38: =INVOICE!B36 -> PUROTEKUTA 55788-52360 | E38: =INVOICE!E36 -> pcs | F38: =INVOICE!F36 -> 5000 | G38: =VLOOKUP(B38,データ!$B$3:$E$85,4,FALSE) -> 500 | I38: =ROUNDUP(F38/G38,0) -> 10 | K38: =ROUND(N38+P38,2)+5 -> 5
A39: 4/13 | B39: =INVOICE!B37 -> PUROTEKUTA 2A4P1-022G | E39: =INVOICE!E37 -> pcs | F39: =INVOICE!F37 -> 11000 | G39: =VLOOKUP(B39,データ!$B$3:$E$85,4,FALSE) -> 500 | I39: =ROUNDUP(F39/G39,0) -> 22 | J39: 1 | K39: =ROUND(N39+P39,2)+10 -> 10
B40: =INVOICE!B38 -> PUROTEKUTA 55788-K0060 | E40: =INVOICE!E38 -> pcs | F40: =INVOICE!F38 -> 5500 | G40: =VLOOKUP(B40,データ!$B$3:$E$85,4,FALSE) -> 500 | I40: =ROUNDUP(F40/G40,0) -> 11 | K40: =ROUND(N40+P40,2)+10 -> 10
A41: 5/13 | B41: =INVOICE!B39 -> PUROTEKUTA 55788-48090 | E41: =INVOICE!E39 -> pcs | F41: =INVOICE!F39 -> 9000 | G41: =VLOOKUP(B41,データ!$B$3:$E$85,4,FALSE) -> 500 | I41: =ROUNDUP(F41/G41,0) -> 18 | J41: 1 | K41: =ROUND(N41+P41,2)+10 -> 10
B42: =INVOICE!B40 -> PUROTEKUTA 55788-K0060 | E42: =INVOICE!E40 -> pcs | F42: =INVOICE!F40 -> 5500 | G42: =VLOOKUP(B42,データ!$B$3:$E$85,4,FALSE) -> 500 | I42: =ROUNDUP(F42/G42,0) -> 11 | K42: =ROUND(N42+P42,2)+10 -> 10
A43: 6/13 | B43: =INVOICE!B41 -> PUROTEKUTA 55788-K0060 | E43: =INVOICE!E41 -> pcs | F43: =INVOICE!F41 -> 13500 | G43: =VLOOKUP(B43,データ!$B$3:$E$85,4,FALSE) -> 500 | I43: =ROUNDUP(F43/G43,0) -> 27 | J43: 1 | K43: =ROUND(N43+P43,2)+20 -> 20
A44: 7/13 | B44: =INVOICE!B42 -> PUROTEKUTA 55788-60110 | E44: =INVOICE!E42 -> pcs | F44: =INVOICE!F42 -> 13000 | G44: =VLOOKUP(B44,データ!$B$3:$E$85,4,FALSE) -> 500 | I44: =ROUNDUP(F44/G44,0) -> 26 | J44: 1 | K44: =ROUND(N44+P44,2)+20 -> 20
B45: =INVOICE!B43 -> RAB0938-V+H450 - N | E45: =INVOICE!E43 -> pcs | F45: =INVOICE!F43 -> 7 | G45: 7 | I45: =ROUNDUP(F45/G45,0) -> 1 | K45: =ROUND(N45+P45,2) -> 0
A46: 8/13-12/13 | B46: =INVOICE!B44 -> MASK 42811 | E46: =INVOICE!E44 -> bag | F46: =INVOICE!F44 -> 12000 | G46: =VLOOKUP(B46,データ!$B$3:$E$85,4,FALSE) -> 120 | I46: =ROUNDUP(F46/G46,0) -> 100 | J46: 5 | K46: =ROUND(N46+P46,2)+100 -> 100
A47: 13/13 | B47: =INVOICE!B45 -> TABLE EDGE MI3 156 | E47: =INVOICE!E45 -> pcs | F47: =INVOICE!F45 -> 240 | G47: =VLOOKUP(B47,データ!$B$3:$E$85,4,FALSE) -> 30 | I47: =ROUNDUP(F47/G47,0) -> 8 | J47: 1 | K47: =ROUND(N47+P47,2)+20 -> 20
A49: 合計 （Total) | F49: =SUMIF(E35:E48,L42,F35:F48) -> 0 | I49: =SUMIF(E35:E48,L42,I35:I48)+SUMIF(E35:E48,L44,I35:I48) -> 0 | J49: =SUM(J35:J48) -> 13 | K49: =SUM(K35:K48) -> 240
F51: =SUMIF(E35:E48,L43,F35:F48) -> 0 | I51: =SUMIF(E35:E48,L43,I35:I48) -> 0
F52: =SUMIF(E35:E48,L44,F35:F48) -> 0
A53: =INVOICE!A50 -> CIF TO NAGOYA PORT
A54: 郵便物の個数 ( Number of pieces, m) : | D54: =F49 -> 0 | E54: =F51 -> 0 | F54: =F52 -> 0 | I54: 署名（ Singnature )
A55: 総重量（Gross weight) Kg : | D55: =K49 -> 240 | E55: =J49 -> 13
A56: 原産国（Country of Origin) :VIETNAM | D56: =1.1*1.5*1.1*6+1.1*1.1*1.4+1.1*1.2*1.8*5+1.1*1.1*1 -> 25.674
A57: 輸送方法 ( Shipped per) : SEA

Sheet IV tong
A1: INVOICE
F5: =INVOICE!G5 -> インボイス作成日（Date): 5/12/2025
A8: 依頼住 (Shipper Address) | F8: =INVOICE!G8 -> Invoice No MASUDA VN-JP 019/25
A10: MASUDA VINYL VIETNAM CO.,LTD
A11: LOT NO1 DONG VANG DINH TRAM INDUSTRIAL ZONE | F11: (原産国) Country of Origin | H11: (仕向先国名) Country of Destination
A12: NENH TOWN VIET YEN DISTRICT BAC GIANG PROVINCE
A13: TEL : 0204 3662 777 | F13: VIETNAM | H13: JAPAN
A14: FAX : 0204 3662 825 | F14: 支払条件 (Terms of Payment)
F15: 20日締め翌月末支払 (Invoice will be closed on 20th every month and payment at end of the following month)
A16: 荷受人(Consigneer)
A19: MASUDA VINYL CO.,LTD
A20: 390ROKUGAIKECYOU KITAKU | F20: 備考 (Remark):
A21: NAGOYA CITY AICHI JAPAN
A22: TEL : 052-901-9373 | F22: P | G22: 有償（Commerical Value)
A23: FAX : 052-901-6943 | G23: 無償（No Commerical Value)
A25: From (発地国) | E25: Via (経由国) | G25: 贈物（Gift)
A26: BACGIANG VIETNAM | E26: CIF | G26: 商品見本（ Sample, No Commercial Value )
A27: To (着地国) | G27: その他（Other)
A28: NAGOYA JAPAN
A30: ラベル内容 (Marks & Nos.) | B30: 内容品の記載 (Description) | D30: 単位 （Unit） | E30: 数量 （Quantity) | F30: 単価 （Unit Price） | H30: 合計 （Total Amount)
K33: Mã HS code | L33: ĐVT 2 | M33: trọng lượng | N33: SL2 | O33: IV | P33: SO SÁNH
A34: 1 | B34: PUROTEKUTA 55788-60110 | D34: =VLOOKUP(B34,データ!$B$3:$L$85,11,FALSE) -> pcs | E34: 13000 | F34: =VLOOKUP(B34,データ!$B$3:$C$85,2,FALSE) -> 0.223 | H34: =F34*E34 -> 2899 | K34: =_xlfn.IFNA(VLOOKUP(B34,データ!$B$3:$O$137,12,0),"") -> 39169092 | L34: =_xlfn.IFNA(VLOOKUP(B34,データ!$B$3:$O$137,13,0),"") -> Kg | M34: =_xlfn.IFNA(VLOOKUP(B34,データ!$B$3:$D$127,3,FALSE),"") -> 25 | N34: =IF(L34="kg",M34*E34/1000,AND(IF(L34="PCE",E34))) -> 325 | O34: =SUMIF(INVOICE!$B$33:$C$45,B34,INVOICE!$F$33:$F$45) -> 13000 | P34: =+E34-O34 -> 0
A35: =A34+1 -> 2 | B35: PUROTEKUTA 55788-16110 | D35: =VLOOKUP(B35,データ!$B$3:$L$85,11,FALSE) -> pcs | E35: 11000 | F35: =VLOOKUP(B35,データ!$B$3:$C$85,2,FALSE) -> 0.223 | H35: =F35*E35 -> 2453 | K35: =_xlfn.IFNA(VLOOKUP(B35,データ!$B$3:$O$137,12,0),"") -> 39169092 | L35: =_xlfn.IFNA(VLOOKUP(B35,データ!$B$3:$O$137,13,0),"") -> Kg | M35: =_xlfn.IFNA(VLOOKUP(B35,データ!$B$3:$D$127,3,FALSE),"") -> 25 | N35: =IF(L35="kg",M35*E35/1000,AND(IF(L35="PCE",E35))) -> 275 | O35: =SUMIF(INVOICE!$B$33:$C$45,B35,INVOICE!$F$33:$F$45) -> 11000 | P35: =+E35-O35 -> 0
A36: =A35+1 -> 3 | B36: PUROTEKUTA 55788-K0060 | D36: =VLOOKUP(B36,データ!$B$3:$L$85,11,FALSE) -> pcs | E36: 24500 | F36: =VLOOKUP(B36,データ!$B$3:$C$85,2,FALSE) -> 0.224 | H36: =F36*E36 -> 5488 | K36: =_xlfn.IFNA(VLOOKUP(B36,データ!$B$3:$O$137,12,0),"") -> 39169092 | L36: =_xlfn.IFNA(VLOOKUP(B36,データ!$B$3:$O$137,13,0),"") -> Kg | M36: =_xlfn.IFNA(VLOOKUP(B36,データ!$B$3:$D$127,3,FALSE),"") -> 23 | N36: =IF(L36="kg",M36*E36/1000,AND(IF(L36="PCE",E36))) -> 563.5 | O36: =SUMIF(INVOICE!$B$33:$C$45,B36,INVOICE!$F$33:$F$45) -> 24500 | P36: =+E36-O36 -> 0
A37: =A36+1 -> 4 | B37: PUROTEKUTA 2A4P1-022G | D37: =VLOOKUP(B37,データ!$B$3:$L$85,11,FALSE) -> pcs | E37: 11000 | F37: =VLOOKUP(B37,データ!$B$3:$C$85,2,FALSE) -> 0.235 | H37: =F37*E37 -> 2585 | K37: =_xlfn.IFNA(VLOOKUP(B37,データ!$B$3:$O$137,12,0),"") -> 39169092 | L37: =_xlfn.IFNA(VLOOKUP(B37,データ!$B$3:$O$137,13,0),"") -> Kg | M37: =_xlfn.IFNA(VLOOKUP(B37,データ!$B$3:$D$127,3,FALSE),"") -> 23.5 | N37: =IF(L37="kg",M37*E37/1000,AND(IF(L37="PCE",E37))) -> 258.5 | O37: =SUMIF(INVOICE!$B$33:$C$45,B37,INVOICE!$F$33:$F$45) -> 11000 | P37: =+E37-O37 -> 0
A38: =A37+1 -> 5 | B38: PUROTEKUTA 55788-48090 | D38: =VLOOKUP(B38,データ!$B$3:$L$85,11,FALSE) -> pcs | E38: 9000 | F38: =VLOOKUP(B38,データ!$B$3:$C$85,2,FALSE) -> 0.251 | H38: =F38*E38 -> 2259 | K38: =_xlfn.IFNA(VLOOKUP(B38,データ!$B$3:$O$137,12,0),"") -> 39169092 | L38: =_xlfn.IFNA(VLOOKUP(B38,データ!$B$3:$O$137,13,0),"") -> Kg | M38: =_xlfn.IFNA(VLOOKUP(B38,データ!$B$3:$D$127,3,FALSE),"") -> 25 | N38: =IF(L38="kg",M38*E38/1000,AND(IF(L38="PCE",E38))) -> 225 | O38: =SUMIF(INVOICE!$B$33:$C$45,B38,INVOICE!$F$33:$F$45) -> 9000 | P38: =+E38-O38 -> 0
A39: =A38+1 -> 6 | B39: PUROTEKUTA 55788-52360 | D39: =VLOOKUP(B39,データ!$B$3:$L$85,11,FALSE) -> pcs | E39: 5000 | F39: =VLOOKUP(B39,データ!$B$3:$C$85,2,FALSE) -> 0.223 | H39: =F39*E39 -> 1115 | K39: =_xlfn.IFNA(VLOOKUP(B39,データ!$B$3:$O$137,12,0),"") -> 39169092 | L39: =_xlfn.IFNA(VLOOKUP(B39,データ!$B$3:$O$137,13,0),"") -> Kg | M39: =_xlfn.IFNA(VLOOKUP(B39,データ!$B$3:$D$127,3,FALSE),"") -> 25 | N39: =IF(L39="kg",M39*E39/1000,AND(IF(L39="PCE",E39))) -> 125 | O39: =SUMIF(INVOICE!$B$33:$C$45,B40,INVOICE!$F$33:$F$45) -> 6000 | P39: =+E40-O39 -> 0
A40: =A39+1 -> 7 | B40: PUROTEKUTA 55788-52350 | D40: =VLOOKUP(B40,データ!$B$3:$L$85,11,FALSE) -> pcs | E40: 6000 | F40: =VLOOKUP(B40,データ!$B$3:$C$85,2,FALSE) -> 0.213 | H40: =F40*E40 -> 1278 | K40: =_xlfn.IFNA(VLOOKUP(B40,データ!$B$3:$O$137,12,0),"") -> 39169092 | L40: =_xlfn.IFNA(VLOOKUP(B40,データ!$B$3:$O$137,13,0),"") -> Kg | M40: =_xlfn.IFNA(VLOOKUP(B40,データ!$B$3:$D$127,3,FALSE),"") -> 23.5 | N40: =IF(L40="kg",M40*E40/1000,AND(IF(L40="PCE",E40))) -> 141 | O40: =SUMIF(INVOICE!$B$33:$C$45,#REF!,INVOICE!$F$33:$F$45) -> 0 | P40: =+E41-O40 -> 4000
A41: =A40+1 -> 8 | B41: TABLE EDGE MG23 | D41: =VLOOKUP(B41,データ!$B$3:$L$85,11,FALSE) -> m | E41: 4000 | F41: =VLOOKUP(B41,データ!$B$3:$C$85,2,FALSE) -> 0.61 | H41: =F41*E41 -> 2440 | K41: =_xlfn.IFNA(VLOOKUP(B41,データ!$B$3:$O$137,12,0),"") -> 39169092 | L41: =_xlfn.IFNA(VLOOKUP(B41,データ!$B$3:$O$137,13,0),"") -> Kg | M41: =_xlfn.IFNA(VLOOKUP(B41,データ!$B$3:$D$127,3,FALSE),"") -> 78 | N41: =IF(L41="kg",M41*E41/1000,AND(IF(L41="PCE",E41))) -> 312 | O41: =SUMIF(INVOICE!$B$33:$C$45,#REF!,INVOICE!$F$33:$F$45) -> 0 | P41: =+E42-O41 -> 240
A42: =A41+1 -> 9 | B42: TABLE EDGE MI3 156 | D42: =VLOOKUP(B42,データ!$B$3:$L$85,11,FALSE) -> pcs | E42: 240 | F42: =VLOOKUP(B42,データ!$B$3:$C$85,2,FALSE) -> 2.875 | H42: =F42*E42 -> 690 | K42: =_xlfn.IFNA(VLOOKUP(B42,データ!$B$3:$O$137,12,0),"") -> 39169092 | L42: =_xlfn.IFNA(VLOOKUP(B42,データ!$B$3:$O$137,13,0),"") -> Kg | M42: =_xlfn.IFNA(VLOOKUP(B42,データ!$B$3:$D$127,3,FALSE),"") -> 691.38 | N42: =IF(L42="kg",M42*E42/1000,AND(IF(L42="PCE",E42))) -> 165.9312 | O42: =SUMIF(INVOICE!$B$33:$C$45,B41,INVOICE!$F$33:$F$45) -> 4000 | P42: =+E43-O42 -> 8000
A43: =A42+1 -> 10 | B43: MASK 42811 | D43: =VLOOKUP(B43,データ!$B$3:$L$85,11,FALSE) -> bag | E43: 12000 | F43: =VLOOKUP(B43,データ!$B$3:$C$85,2,FALSE) -> 0.2 | H43: =F43*E43 -> 2400 | K43: =_xlfn.IFNA(VLOOKUP(B43,データ!$B$3:$O$137,12,0),"") -> 0 | L43: =_xlfn.IFNA(VLOOKUP(B43,データ!$B$3:$O$137,13,0),"") -> 0 | M43: =_xlfn.IFNA(VLOOKUP(B43,データ!$B$3:$D$127,3,FALSE),"") -> 83.3 | N43: =IF(L43="kg",M43*E43/1000,AND(IF(L43="PCE",E43))) -> FALSE | O43: =SUMIF(INVOICE!$B$33:$C$45,B42,INVOICE!$F$33:$F$45) -> 240 | P43: =+E44-O43 -> -233
A44: =A43+1 -> 11 | B44: RAB0938-V+H450 - N | D44: =VLOOKUP(B44,データ!$B$3:$L$185,11,FALSE) -> pcs | E44: 7 | F44: =VLOOKUP(B44,データ!$B$3:$C$185,2,FALSE) -> 2.91 | H44: =F44*E44 -> 20.37 | K44: =_xlfn.IFNA(VLOOKUP(B44,データ!$B$3:$O$137,12,0),"") -> 39169092 | L44: =_xlfn.IFNA(VLOOKUP(B44,データ!$B$3:$O$137,13,0),"") -> Kg | M44: =_xlfn.IFNA(VLOOKUP(B44,データ!$B$3:$D$127,3,FALSE),"") -> 435.04478 | N44: =IF(L44="kg",M44*E44/1000,AND(IF(L44="PCE",E44))) -> 3.0453134 | O44: =SUMIF(INVOICE!$B$33:$C$45,B43,INVOICE!$F$33:$F$45) -> 12000 | P44: =+E45-O44 -> -12000
A45: =A44+1 -> 12 | K45: =_xlfn.IFNA(VLOOKUP(B45,データ!$B$3:$O$137,12,0),"") | L45: =_xlfn.IFNA(VLOOKUP(B45,データ!$B$3:$O$137,13,0),"") | M45: =_xlfn.IFNA(VLOOKUP(B45,データ!$B$3:$D$127,3,FALSE),"") | N45: =IF(L45="kg",M45*E45/1000,AND(IF(L45="PCE",E45))) -> FALSE | O45: =SUMIF(INVOICE!$B$33:$C$45,B44,INVOICE!$F$33:$F$45) -> 7 | P45: =+E46-O45 -> -7
A46: =A45+1 -> 13 | K46: =_xlfn.IFNA(VLOOKUP(B46,データ!$B$3:$O$137,12,0),"") | L46: =_xlfn.IFNA(VLOOKUP(B46,データ!$B$3:$O$137,13,0),"") | M46: =_xlfn.IFNA(VLOOKUP(B46,データ!$B$3:$D$127,3,FALSE),"") | N46: =IF(L46="kg",M46*E46/1000,AND(IF(L46="PCE",E46))) -> FALSE | O46: =SUMIF(INVOICE!$B$33:$C$45,B45,INVOICE!$F$33:$F$45) -> 0 | P46: =+E47-O46 -> 0
A47: =A46+1 -> 14 | K47: =_xlfn.IFNA(VLOOKUP(B47,データ!$B$3:$O$137,12,0),"") | L47: =_xlfn.IFNA(VLOOKUP(B47,データ!$B$3:$O$137,13,0),"") | M47: =_xlfn.IFNA(VLOOKUP(B47,データ!$B$3:$D$127,3,FALSE),"") | N47: =IF(L47="kg",M47*E47/1000,AND(IF(L47="PCE",E47))) -> FALSE | O47: =SUMIF(INVOICE!$B$33:$C$45,B46,INVOICE!$F$33:$F$45) -> 0 | P47: =+E48-O47 -> 0
A48: =A47+1 -> 15 | K48: =_xlfn.IFNA(VLOOKUP(B48,データ!$B$3:$O$137,12,0),"") | L48: =_xlfn.IFNA(VLOOKUP(B48,データ!$B$3:$O$137,13,0),"") | M48: =_xlfn.IFNA(VLOOKUP(B48,データ!$B$3:$D$127,3,FALSE),"") | N48: =IF(L48="kg",M48*E48/1000,AND(IF(L48="PCE",E48))) -> FALSE | O48: =SUMIF(INVOICE!$B$33:$C$45,B47,INVOICE!$F$33:$F$45) -> 0 | P48: =+E49-O48 -> 0
A49: 合計 （Total) | H49: =SUM(H34:I48) -> 23627.37
A51: 原産国 (Country of Origin) : VIETNAM | F51: 署名（ Singnature )
A52: CIF TO NAGOYA PORT

Sheet PL tong
A1: PACKING LIST
G5: =INVOICE!G5 -> インボイス作成日（Date): 5/12/2025
A8: 依頼住 (Shipper Address) | G8: =INVOICE!G8 -> Invoice No MASUDA VN-JP 019/25
A10: MASUDA VINYL VIETNAM CO.,LTD
A11: LOT NO1 DONG VANG DINH TRAM INDUSTRIAL ZONE | G11: (原産国) Country of Origin | I11: (仕向先国名) Country of Destination
A12: NENH TOWN VIET YEN DISTRICT BAC GIANG PROVINCE
A13: TEL : 0204 3662 777 | G13: VIETNAM | I13: JAPAN
A14: FAX : 0204 3662 825 | G14: 支払条件 (Terms of Payment)
G15: 20日締め翌月末支払 (Invoice will be closed on 20th every month and payment at end of the following month)
A17: 荷受人(Consigneer)
A20: MASUDA VINYL CO.,LTD | G20: 備考 (Remark):
A21: 390ROKUGAIKECYOU KITAKU
A22: NAGOYA CITY AICHI JAPAN | G22: P | H22: 有償（Commerical Value)
A23: TEL : 052-901-9373 | H23: 無償（No Commerical Value)
A24: FAX : 052-901-6943
H25: 贈物（Gift)
A26: From (発地国) | E26: Via (経由国) | H26: 商品見本（ Sample, No Commercial Value )
A27: BACGIANG VIETNAM | E27: CIF | H27: その他（Other)
A28: To (着地国)
A29: NAGOYA JAPAN
A31: ラベル内容 (Marks & Nos.) | B31: 内容品の記載 (Description) | D31: 単位 （Unit） | E31: 数量 （Quantity) | F31: 梱包 （Packing） | H31: 箱数 ( Number of Boxs) | I31: パレット数 ( Number of Pallets) | J31: 総重量 (Gross weight)
L34: trọng lượng | M34: Net weight | N34: Túi | O34: Thùng
A35: 1 | B35: ='IV tong'!B34:C34 -> PUROTEKUTA 55788-60110 | D35: ='IV tong'!D34 -> pcs | E35: ='IV tong'!E34 -> 13000 | F35: =VLOOKUP(B35,データ!$B$3:$E$85,4,FALSE) -> 500 | H35: =E35/F35 -> 26 | I35: 5 | J35: =M35+N35+O35 -> 351 | K35: pcs | L35: =VLOOKUP(B35,データ!$B$3:$D$89,3,FALSE) -> 25 | M35: =E35*L35/1000 -> 325 | O35: =H35*1 -> 26
A36: =A35+1 -> 2 | B36: ='IV tong'!B35:C35 -> PUROTEKUTA 55788-16110 | D36: ='IV tong'!D35 -> pcs | E36: ='IV tong'!E35 -> 11000 | F36: =VLOOKUP(B36,データ!$B$3:$E$85,4,FALSE) -> 500 | H36: =E36/F36 -> 22 | J36: =M36+N36+O36 -> 297 | L36: =VLOOKUP(B36,データ!$B$3:$D$89,3,FALSE) -> 25 | M36: =E36*L36/1000 -> 275 | O36: =H36*1 -> 22
A37: =A36+1 -> 3 | B37: ='IV tong'!B36:C36 -> PUROTEKUTA 55788-K0060 | D37: ='IV tong'!D36 -> pcs | E37: ='IV tong'!E36 -> 24500 | F37: =VLOOKUP(B37,データ!$B$3:$E$85,4,FALSE) -> 500 | H37: =E37/F37 -> 49 | J37: =M37+N37+O37 -> 612.5 | K37: m | L37: =VLOOKUP(B37,データ!$B$3:$D$89,3,FALSE) -> 23 | M37: =E37*L37/1000 -> 563.5 | O37: =H37*1 -> 49
A38: =A37+1 -> 4 | B38: ='IV tong'!B37:C37 -> PUROTEKUTA 2A4P1-022G | D38: ='IV tong'!D37 -> pcs | E38: ='IV tong'!E37 -> 11000 | F38: =VLOOKUP(B38,データ!$B$3:$E$85,4,FALSE) -> 500 | H38: =E38/F38 -> 22 | J38: =M38+N38+O38 -> 280.5 | K38: bag | L38: =VLOOKUP(B38,データ!$B$3:$D$89,3,FALSE) -> 23.5 | M38: =E38*L38/1000 -> 258.5 | O38: =H38*1 -> 22
A39: =A38+1 -> 5 | B39: ='IV tong'!B38:C38 -> PUROTEKUTA 55788-48090 | D39: ='IV tong'!D38 -> pcs | E39: ='IV tong'!E38 -> 9000 | F39: =VLOOKUP(B39,データ!$B$3:$E$85,4,FALSE) -> 500 | H39: =E39/F39 -> 18 | J39: =M39+N39+O39 -> 243 | L39: =VLOOKUP(B39,データ!$B$3:$D$89,3,FALSE) -> 25 | M39: =E39*L39/1000 -> 225 | O39: =H39*1 -> 18
A40: =A39+1 -> 6 | B40: ='IV tong'!B39:C39 -> PUROTEKUTA 55788-52360 | D40: ='IV tong'!D39 -> pcs | E40: ='IV tong'!E39 -> 5000 | F40: =VLOOKUP(B40,データ!$B$3:$E$85,4,FALSE) -> 500 | H40: =E40/F40 -> 10 | J40: =M40+N40+O40 -> 135 | L40: =VLOOKUP(B40,データ!$B$3:$D$89,3,FALSE) -> 25 | M40: =E40*L40/1000 -> 125 | O40: =H40*1 -> 10
A41: =A40+1 -> 7 | B41: ='IV tong'!B40:C40 -> PUROTEKUTA 55788-52350 | D41: ='IV tong'!D40 -> pcs | E41: ='IV tong'!E40 -> 6000 | F41: =VLOOKUP(B41,データ!$B$3:$E$85,4,FALSE) -> 500 | H41: =E41/F41 -> 12 | J41: =M41+N41+O41 -> 153 | L41: =VLOOKUP(B41,データ!$B$3:$D$89,3,FALSE) -> 23.5 | M41: =E41*L41/1000 -> 141 | O41: =H41*1 -> 12
A42: =A41+1 -> 8 | B42: ='IV tong'!B41:C41 -> TABLE EDGE MG23 | D42: ='IV tong'!D41 -> m | E42: ='IV tong'!E41 -> 4000 | F42: =VLOOKUP(B42,データ!$B$3:$E$85,4,FALSE) -> 50 | H42: =E42/F42 -> 80 | I42: 1 | J42: =M42+N42+O42 -> 392 | L42: =VLOOKUP(B42,データ!$B$3:$D$198,3,FALSE) -> 78 | M42: =E42*L42/1000 -> 312 | O42: =H42*1 -> 80
A43: =A42+1 -> 9 | B43: ='IV tong'!B42:C42 -> TABLE EDGE MI3 156 | D43: ='IV tong'!D42 -> pcs | E43: ='IV tong'!E42 -> 240 | F43: =VLOOKUP(B43,データ!$B$3:$E$85,4,FALSE) -> 30 | H43: =E43/F43 -> 8 | J43: =M43+N43+O43 -> 173.9312 | L43: =VLOOKUP(B43,データ!$B$3:$D$198,3,FALSE) -> 691.38 | M43: =E43*L43/1000 -> 165.9312 | O43: =H43*1 -> 8
A44: =A43+1 -> 10 | B44: ='IV tong'!B43:C43 -> MASK 42811 | D44: ='IV tong'!D43 -> bag | E44: ='IV tong'!E43 -> 12000 | F44: =VLOOKUP(B44,データ!$B$3:$E$85,4,FALSE) -> 120 | H44: =E44/F44 -> 100 | I44: 5 | J44: =M44+N44+O44 -> 1049.6 | L44: =VLOOKUP(B44,データ!$B$3:$D$198,3,FALSE) -> 83.3 | M44: =E44*L44/1000 -> 999.6 | O44: =H44*0.5 -> 50
A45: =A44+1 -> 11 | L45: =VLOOKUP(B45,データ!$B$3:$D$198,3,FALSE) -> #N/A | M45: =E45*L45/1000 -> #N/A | O45: =H45*1 -> 0
A46: =A45+1 -> 12 | L46: =VLOOKUP(B46,データ!$B$3:$D$198,3,FALSE) -> #N/A | M46: =E46*L46/1000 -> #N/A | O46: =H46*1 -> 0
A47: =A46+1 -> 13 | L47: =VLOOKUP(B47,データ!$B$3:$D$198,3,FALSE) -> #N/A | M47: =E47*L47/1000 -> #N/A | O47: =H47*1 -> 0
L48: =VLOOKUP(B48,データ!$B$3:$D$198,3,FALSE) -> #N/A | M48: =E48*L48/1000 -> #N/A | O48: =H48*1 -> 0
A49: 合計 （Total) | E49: =SUMIF(D35:D48,K35,E35:E48) -> 79740 | H49: =SUMIF(D35:D48,K35,H35:H48)+ SUMIF(D35:D48,K38,H35:H48) -> 267 | I49: =SUM(I35:I48) -> 11 | J49: =SUM(J35:J48)+220 -> 3907.5312
E51: =SUMIF(D35:D48,K37,E35:E48) -> 4000 | H51: =SUMIF(D35:D48,K37,H35:H48) -> 80
A52: CIF TO NAGOYA PORT
A53: 郵便物の個数 ( Number of pieces, m) : | D53: =E49 -> 79740 | E53: =E51 -> 4000 | H53: 署名（ Singnature )
A54: 総重量（Gross weight) Kg : | D54: =J49 -> 3907.5312 | E54: =I49 -> 11
A55: 原産国（Country of Origin) :VIETNAM | D55: =1.1*1.5*1.5*6+1.1*1.1*1.9*5 -> 26.345
A56: 輸送方法 ( Shipped per) : SEA
D68: 品名 | E68: 重さ | F68: 数量 | G68: 製品重量 | H68: 袋 | I68: 段ボール | J68: 総重量
D69: 4140 | E69: 100 | F69: =#REF! -> #REF! | G69: =F69*E69/1000 -> #REF! | H69: =#REF!*6*0.38/1000 -> #REF! | I69: =#REF!*0.6 -> #REF! | J69: =G69+H69+I69 -> #REF!
D70: 4080 | E70: 53 | F70: =#REF! -> #REF! | G70: =F70*E70/1000 -> #REF! | H70: =#REF!*7*0.38/1000 -> #REF! | I70: =#REF!*600/1000 -> #REF! | J70: =G70+H70+I70 -> #REF! | K70: =G69+G70 -> #REF!
D71: 4090 | E71: 60 | F71: =#REF! -> #REF! | G71: =F71*E71/1000 -> #REF! | H71: =#REF!*7*0.38/1000 -> #REF! | I71: =#REF!*600/1000 -> #REF! | J71: =G71+H71+I71 -> #REF!
D72: 4120 | E72: 43 | F72: =#REF! -> #REF! | G72: =F72*E72/1000 -> #REF! | H72: =#REF!*7*0.38/1000 -> #REF! | I72: =#REF!*600/1000 -> #REF! | J72: =G72+H72+I72 -> #REF!
D73: 4130 | E73: 28 | F73: =#REF! -> #REF! | G73: =F73*E73/1000 -> #REF! | H73: =#REF!*7*0.38/1000 -> #REF! | I73: =#REF!*600/1000 -> #REF! | J73: =G73+H73+I73 -> #REF!
D74: 100L | E74: 4.3 | F74: =#REF! -> #REF! | G74: =F74*E74/1000 -> #REF! | I74: =F74/3000*0.6 -> #REF! | J74: =I74+G74 -> #REF!
D75: 200L | E75: 7.2 | G75: =F75*E75/1000 -> 0 | I75: =F75/1500*0.6 -> 0 | J75: =I75+G75 -> 0
D76: 290L | E76: 12.4 | G76: =F76*E76/1000 -> 0 | I76: =16*0.6 -> 9.6 | J76: =I76+G76 -> 9.6
D77: 2.5ø 100L | E77: 0.8 | F77: =#REF! -> #REF! | G77: =F77*E77/1000 -> #REF! | I77: =16*0.6 -> 9.6 | J77: =I77+G77 -> #REF!
D78: 3ø 100L | E78: 0.8 | G78: =F78*E78/1000 -> 0 | I78: =2*0.6 -> 1.2 | J78: =I78+G78 -> 1.2
C79: =16.7*50 -> 835 | D79: 3ø 150L | E79: 1.1 | G79: =F79*E79/1000 -> 0 | I79: =1*0.6 -> 0.6 | J79: =I79+G79 -> 0.6
D80: 4ø 100L | E80: 1.1 | F80: =#REF! -> #REF! | G80: =F80*E80/1000 -> #REF! | I80: =3*0.6 -> 1.8 | J80: =I80+G80 -> #REF!
C81: 上達 | D81: 5ø 183L | E81: 3.7 | G81: =F81*E81/1000 -> 0 | I81: =F81/1500*0.6 -> 0 | J81: =I81+G81 -> 0
C82: =3.9/50*100 -> 7.8 | J82: =I82+G82 -> 0
C83: =E84/50*100 -> 16.8 | D83: 23MG | E83: 3.9 | F83: =#REF! -> #REF! | G83: =F83/50*E83 -> #REF! | J83: =I83+G83 -> #REF!
D84: MI3 | E84: 8.4 | F84: =#REF! -> #REF! | G84: =E84*F84/50 -> #REF! | J84: =I84+G84 -> #REF!
B85: =50*16.8 -> 840 | C85: 450x1800 | D85: MI3 156 | E85: =4140*167/1000/1000 -> 0.69138 | F85: =#REF! -> #REF! | G85: =E85*F85 -> #REF! | I85: =12*1 -> 12 | J85: =I85+G85 -> #REF! | K85: 4140 | L85: 1000mm=167g
C86: 600x1800 | D86: MI3 26 | E86: =4416*167/1000/1000 -> 0.737472 | F86: =#REF! -> #REF! | G86: =F86*E86 -> #REF! | I86: =F86/30*1 -> #REF! | J86: =I86+G86 -> #REF! | K86: 4416 | L86: 1000mm=167g
C87: 900x1800 | D87: MI3 36 | E87: 0.84 | G87: =F87*E87 -> 0 | I87: =F87/25*1 -> 0 | J87: =I87+G87 -> 0
C88: 750x1800 | D88: MI3 256 | E88: 0.77 | G88: =F88*E88 -> 0 | I88: =F88/25*1 -> 0 | J88: =I88+G88 -> 0
D89: MI3 155 | E89: 0.624 | F89: =E52 -> 0 | G89: =F89*E89 -> 0 | I89: =F89/25*1 -> 0 | J89: =I89+G89 -> 0
D90: MI3 25 | E90: 0.673 | G90: =F90*E90 -> 0 | I90: =F90/25*1 -> 0 | J90: =I90+G90 -> 0
B91: =16.8/1000 -> 0.0168 | D91: P 1335L | E91: 21.6 | G91: =F91*E91/1000 -> 0 | I91: =F91/500*1 -> 0 | J91: =I91+G91 -> 0
D92: P 1422L | E92: 24 | F92: =E55 -> 0 | G92: =F92*E92/1000 -> 0 | I92: =F92/500*1 -> 0 | J92: =I92+G92 -> 0
D93: P1383L | E93: 21.7 | F93: =E56 -> 0 | G93: =F93*E93/1000 -> 0 | I93: =F93/500*1 -> 0 | J93: =I93+G93 -> 0
D94: DIP TUBE | E94: 0.052 | F94: =E64 -> 0 | G94: =F94*E94 -> 0 | I94: =F94/100*1 -> 0 | J94: =I94+G94 -> 0

Sheet Yeu cau thanh toan
J1: 45863
A2: 御請求書 HÓA ĐƠN YÊU CẦU THANH TOÁN
A9: 株式会社 MASUDA VINYL CO.,LTD 様
A10: Kính gửi :
G13: 〖振り込む先〗
A14: 毎度有り難うございます。 | G14: Thông tin chuyển khoản
A15: Xin chân thành cảm ơn quý công ty. | G15: 銀行： BANK FOR FOREIGN TRADE OF VIETNAM - BAC GIANG BRANCH
A16: 下記の通り、御請求申し上げます。 | G16: (Ngân hàng)
A17: Chúng tôi xin phép gửi yêu cầu thanh toán bên dưới. | G17: SWIFT CODE : BFTVVNVX073
G18: 口座番号: 0731370684223
G19: (Số tài khoản)
G20: MASUDA VINYL VIETNAM CO.,LTD
B22: 前回請求額 Nợ cũ | C22: 御入金額 Đã thanh toán | D22: 繰越額 Nợ tồn | E22: 御買上額 Mua hàng lần mới nhất | F22: 消費税 Tiền thuế | G22: 今回御請求額 Tổng số tiền lần này | H22: 相殺金額 Đối trừ công nợ | I22: 差引き請求額 Số tiền yêu cẩu thanh toán
B23: 0 | C23: 0 | D23: =B23-C23 -> 0 | E23: =I53 -> 20818.6 | F23: =E23*0 -> 0 | G23: =E23+F23+D23 -> 20818.6 | H23: =J63 -> 0 | I23: =G23-H23 -> 20818.6
A25: 請 求 明 細
A26: Chi tiết thanh toán
A28: 伝票No Số phiếu | C28: ベトナム出荷日 Ngày xuất phía VN | D28: 商品名/規格 Tên hàng / Quy cách | F28: 数量 Số lượng | G28: 単位 Đơn vị | H28: 単価 Đơn giá | I28: 金額 Số tiền | J28: 摘要 Chú thích
A29: MASUDA | C29: 45878 | D29: TABLE EDGE MG23 | F29: 4000 | G29: pcs | H29: =VLOOKUP(D29,データ!B3:E87,2,FALSE) -> 0.61 | I29: =H29*F29 -> 2440 | J29: =F29/50 -> 80 | L29: 品名 | M29: 単価 | N29: 単位 | O29: 出荷数 | P29: 梱包
A30: VN-JP 013 | L30: MASUGOMU 4140 | M30: 0.71 | N30: pcs | O30: =VLOOKUP(L30,[1]原紙!$D$29:$F$62,3,FALSE) -> #N/A | P30: =O30/180 -> #N/A
A31: MASUDA | C31: =C29 -> 45878 | D31: PUROTEKUTA 2A4P1-022G | F31: 10000 | G31: pcs | H31: =VLOOKUP(D31,データ!B5:E89,2,FALSE) -> 0.235 | I31: =H31*F31 -> 2350 | J31: =F31/500 -> 20 | L31: MASUGOMU 4080 | M31: 0.4 | N31: pcs | O31: =VLOOKUP(L31,[2]原紙!$D$29:$F$62,3,FALSE) -> #N/A | P31: =O31/350 -> #N/A
A32: =A30 -> VN-JP 013 | L32: TABLE EDGE MG23 | M32: 0.5 | N32: m | O32: =VLOOKUP(L32,[2]原紙!$D$29:$F$62,3,FALSE) -> #N/A | P32: =O32/50 -> #N/A
A33: MASUDA | C33: =C29 -> 45878 | D33: PUROTEKUTA 55788-48090 | F33: 9000 | G33: pcs | H33: =VLOOKUP(D33,データ!B9:E93,2,FALSE) -> 0.251 | I33: =H33*F33 -> 2259 | J33: =F33/500 -> 18
A34: =A30 -> VN-JP 013
A35: MASUDA | C35: =C29 -> 45878 | D35: PUROTEKUTA 55788-60110 | F35: 11000 | G35: pcs | H35: =VLOOKUP(D35,データ!B11:E95,2,FALSE) -> 0.223 | I35: =H35*F35 -> 2453 | J35: =F35/500 -> 22 | L35: SHEET JOINT 100L (5226-1000) | M35: 0.037 | N35: pcs | O35: =VLOOKUP(L35,[1]原紙!$D$29:$F$62,3,FALSE) -> #N/A | P35: =O35/3000 -> #N/A
A36: =A30 -> VN-JP 013 | L36: SHEET JOINT 150L | M36: 0.05 | N36: pcs | O36: =VLOOKUP(L36,[1]原紙!$D$29:$F$62,3,FALSE) -> #N/A | P36: =O36/1500 -> #N/A
A37: MASUDA | C37: =C29 -> 45878 | D37: PUROTEKUTA 55788-16110 | F37: 11000 | G37: pcs | H37: =VLOOKUP(D37,データ!B13:E97,2,FALSE) -> 0.223 | I37: =H37*F37 -> 2453 | J37: =F37/500 -> 22 | L37: SHEET JOINT 200L | M37: 0.07 | N37: pcs | O37: =VLOOKUP(L37,[1]原紙!$D$29:$F$62,3,FALSE) -> #N/A | P37: =O37/1500 -> #N/A
A38: =A30 -> VN-JP 013 | L38: SHEET JOINT 290L | M38: 0.08 | N38: pcs | O38: =VLOOKUP(L38,[1]原紙!$D$29:$F$62,3,FALSE) -> #N/A | P38: =O38/1000 -> #N/A
A39: MASUDA | C39: =C31 -> 45878 | D39: PUROTEKUTA 55788-K0060 | F39: 25000 | G39: pcs | H39: =VLOOKUP(D39,データ!B15:E107,2,FALSE) -> 0.224 | I39: =H39*F39 -> 5600 | J39: =F39/500 -> 50 | L39: TABLE EDGE MI3 | M39: 0.587 | N39: m | O39: =VLOOKUP(L39,[1]原紙!$D$29:$F$62,3,FALSE) -> #N/A | P39: =O39/50 -> #N/A
A40: =A32 -> VN-JP 013 | L40: TABLE EDGE MI3 156 | M40: 2.875 | N40: pcs | O40: =VLOOKUP(L40,[1]原紙!$D$29:$F$62,3,FALSE) -> 205 | P40: =O40/30 -> 6.8333333
A41: MASUDA | C41: =C33 -> 45878 | D41: PUROTEKUTA 55788-52350 | F41: 4000 | G41: pcs | H41: =VLOOKUP(D41,データ!B19:E112,2,FALSE) -> 0.213 | I41: =H41*F41 -> 852 | J41: =F41/500 -> 8
A42: =A34 -> VN-JP 013
A43: MASUDA | C43: =C35 -> 45878 | D43: PUROTEKUTA 55788-52360 | F43: 4000 | G43: pcs | H43: =VLOOKUP(D43,データ!B21:E114,2,FALSE) -> 0.223 | I43: =H43*F43 -> 892 | J43: =F43/500 -> 8
A44: =A36 -> VN-JP 013
A45: MASUDA | C45: =C39 -> 45878 | D45: DIP TUBE | F45: 680 | G45: pcs | H45: =VLOOKUP(D45,データ!B25:E118,2,FALSE) -> 1.22 | I45: =H45*F45 -> 829.6 | J45: =F45/100 -> 6.8
A46: =A40 -> VN-JP 013
A47: MASUDA | C47: =C41 -> 45878 | D47: TABLE EDGE MI3 156 | F47: 240 | G47: pcs | H47: =VLOOKUP(D47,データ!B27:E120,2,FALSE) -> 2.875 | I47: =H47*F47 -> 690 | J47: =F47/30 -> 8
A48: =A42 -> VN-JP 013
H51: 合計 Tổng | I51: =SUM(I29:I50) -> 20818.6 | L51: MASUGOMU 4120 | M51: 1.22 | N51: pcs | O51: =VLOOKUP(L51,[1]原紙!$D$29:$F$62,3,FALSE) -> 10080 | P51: =O51/360 -> 28
H52: 消費税 Thuế VAT | I52: =I51*0 -> 0 | L52: MASUGOMU 4130 | M52: 1.22 | N52: pcs | O52: =VLOOKUP(L52,[1]原紙!$D$29:$F$62,3,FALSE) -> 10260 | P52: =O52/540 -> 19
H53: 税込合計 Tổng cả thuế | I53: =I51+I52 -> 20818.6 | L53: MASUGOMU 4240 | M53: 0.34 | N53: pcs | O53: =VLOOKUP(L53,[1]原紙!$D$29:$F$62,3,FALSE) -> 22320 | P53: =O53/360 -> 62
L54: PUROTEKUTA 55788-48080 | M54: 0.208 | N54: pcs | O54: =VLOOKUP(L54,[1]原紙!$D$29:$F$62,3,FALSE) -> #N/A | P54: =O54/500 -> #N/A
L55: PUROTEKUTA 55788-K0060 | M55: 0.178 | N55: pcs | O55: =VLOOKUP(L55,[1]原紙!$D$29:$F$62,3,FALSE) -> #N/A | P55: =O55/500 -> #N/A

Sheet HS code
A3: TÊN SP | C3: MÃ HS
A4: MASUGOMU 4140 | C4: 39161020
A5: MASUGOMU 4080 | C5: 39161020
A6: TABLE EDGE MG23 | C6: 39169099
A7: KATEKUSU 3ø 100L | C7: 39169099
A8: KATEKUSU 3ø 150L | C8: 39169099
A9: KATEKUSU 4ø 100L | C9: 39169099
A10: KATEKUSU 5ø 183L | C10: 39169099
A11: SHEET JOINT | C11: 39269049
A12: TABLE EDGE MI3 | C12: 39169099
A13: TABLE EDGE MI3 156 | C13: 39169099
A14: TABLE EDGE MI3 26 | C14: 39169099
A15: PUROTEKUTA 1350L | C15: 39169099
... A18: DIP TUBE | C18: 39173290
C105: =SUM(C74:C104) -> 0

Sheet データ
A2: No | B2: 品名 | C2: 単価 | D2: 重さ | E2: 梱包 | F2: 出荷数 | G2: 箱数 | H2: 使用材 | I2: 袋 | J2: 段ボール | K2: 総数量 | L2: 単位 | M2: Mã HS code | N2: SL2
A3: 1 | B3: MASUGOMU 4140 | C3: 0.78 | D3: 100 | E3: 180 | F3: =_xlfn.IFNA(VLOOKUP(B3,'PACKING LIST'!$B$35:$F$54,5,FALSE),0) -> 0 | G3: =ROUNDUP(F3/E3,0) -> 0 | H3: =F3*D3/1000 -> 0 | I3: =G3*6*0.4/1000 -> 0 | J3: =G3*0.7 -> 0 | K3: =J3+I3+H3 -> 0 | L3: pcs | M3: 39161020 | N3: Kg
A4: =A3+1 -> 2 | B4: MASUGOMU 4080 | C4: =0.44 -> 0.44 | D4: 53 | E4: 350 | F4: =_xlfn.IFNA(VLOOKUP(B4,'PACKING LIST'!$B$35:$F$54,5,FALSE),0) -> 0 | G4: =ROUNDUP(F4/E4,0) -> 0 | H4: =F4*D4/1000 -> 0 | I4: =G4*7*0.4/1000 -> 0 | J4: =G4*0.7 -> 0 | K4: =J4+I4+H4 -> 0 | L4: pcs | M4: 39161020 | N4: Kg
A5: 3 | B5: MASUGOMU 4090 | C5: 0.49 | D5: 60 | E5: 360 | F5: =_xlfn.IFNA(VLOOKUP(B5,'PACKING LIST'!$B$35:$F$54,5,FALSE),0) -> 0 | G5: =ROUNDUP(F5/E5,0) -> 0 | H5: =F5*D5/1000 -> 0 | I5: =G5*7*0.4/1000 -> 0 | J5: =G5*0.7 -> 0 | K5: =J5+I5+H5 -> 0 | L5: pcs | M5: 39161020 | N5: Kg
A6: =A5+1 -> 4 | B6: MASUGOMU 4120 | C6: =0.38 -> 0.38 | D6: 43 | E6: 360 | F6: =_xlfn.IFNA(VLOOKUP(B6,'PACKING LIST'!$B$35:$F$54,5,FALSE),0) -> 0 | G6: =ROUNDUP(F6/E6,0) -> 0 | H6: =F6*D6/1000 -> 0 | I6: =G6*7*0.4/1000 -> 0 | J6: =G6*0.7 -> 0 | K6: =J6+I6+H6 -> 0 | L6: pcs | M6: 39161020 | N6: Kg
A7: =A6+1 -> 5 | B7: MASUGOMU 4130 | C7: =0.25 -> 0.25 | D7: 28 | E7: 540 | F7: =_xlfn.IFNA(VLOOKUP(B7,'PACKING LIST'!$B$35:$F$54,5,FALSE),0) -> 0 | G7: =ROUNDUP(F7/E7,0) -> 0 | H7: =F7*D7/1000 -> 0 | I7: =G7*7*0.4/1000 -> 0 | J7: =G7*0.7 -> 0 | K7: =J7+I7+H7 -> 0 | L7: pcs | M7: 39161020 | N7: Kg
A8: =A7+1 -> 6 | B8: MASUGOMU 4240 | C8: =0.38 -> 0.38 | D8: 43 | E8: 360 | F8: =_xlfn.IFNA(VLOOKUP(B8,'PACKING LIST'!$B$35:$F$54,5,FALSE),0) -> 0 | G8: =ROUNDUP(F8/E8,0) -> 0 | H8: =F8*D8/1000 -> 0 | I8: =G8*7*0.4/1000 -> 0 | J8: =G8*0.7 -> 0 | K8: =J8+I8+H8 -> 0 | L8: pcs | M8: 39161020 | N8: Kg
A9: =A8+1 -> 7 | B9: TABLE EDGE MG23 | C9: 0.61 | D9: =3.9/50*1000 -> 78 | E9: 50 | F9: =_xlfn.IFNA(VLOOKUP(B9,'PACKING LIST'!$B$35:$F$54,5,FALSE),0) -> 4000 | G9: =ROUNDUP(F9/E9,0) -> 80 | H9: =G9*D9 -> 6240 | J9: =G9*0 -> 0 | K9: =J9+I9+H9 -> 6240 | L9: m | M9: 39169092 | N9: Kg
A10: =A9+1 -> 8 | B10: KATEKUSU 2.5ø 73L | C10: 0.011 | D10: 0.7 | E10: 20000 | F10: =_xlfn.IFNA(VLOOKUP(B10,'PACKING LIST'!$B$35:$F$54,5,FALSE),0) -> 0 | G10: =ROUNDUP(F10/E10,0) -> 0 | H10: =F10*D10/1000 -> 0 | J10: =G10*0.7 -> 0 | K10: =J10+I10+H10 -> 0 | L10: pcs | M10: 39169092 | N10: Kg
A11: =A10+1 -> 9 | B11: KATEKUSU 2.5ø 50L | C11: 0.01 | D11: 0.7 | E11: 20000 | F11: =_xlfn.IFNA(VLOOKUP(B11,'PACKING LIST'!$B$35:$F$54,5,FALSE),0) -> 0 | G11: =ROUNDUP(F11/E11,0) -> 0 | H11: =F11*D11/1000 -> 0 | J11: =G11*0.7 -> 0 | K11: =J11+I11+H11 -> 0 | L11: pcs | M11: 39169092 | N11: Kg
A12: =A10+1 -> 9 | B12: KATEKUSU 2.5ø 95L | C12: 0.013 | D12: 0.7 | E12: 20000 | F12: =_xlfn.IFNA(VLOOKUP(B12,'PACKING LIST'!$B$35:$F$54,5,FALSE),0) -> 0 | G12: =ROUNDUP(F12/E12,0) -> 0 | H12: =F12*D12/1000 -> 0 | J12: =G12*0.7 -> 0 | K12: =J12+I12+H12 -> 0 | L12: pcs | M12: 39169092 | N12: Kg
A13: =A10+1 -> 9 | B13: KATEKUSU 2.5ø 100L | C13: 0.013 | D13: 0.8 | E13: 20000 | F13: =_xlfn.IFNA(VLOOKUP(B13,'PACKING LIST'!$B$35:$F$54,5,FALSE),0) -> 0 | G13: =ROUNDUP(F13/E13,0) -> 0 | H13: =F13*D13/1000 -> 0 | J13: =G13*0.7 -> 0 | K13: =J13+I13+H13 -> 0 | L13: pcs | M13: 39169092 | N13: Kg
A14: =A12+1 -> 10 | B14: KATEKUSU 2.5ø 135L | C14: 0.015 | D14: 0.8 | E14: 20000 | F14: =_xlfn.IFNA(VLOOKUP(B14,'PACKING LIST'!$B$35:$F$54,5,FALSE),0) -> 0 | G14: =ROUNDUP(F14/E14,0) -> 0 | H14: =F14*D14/1000 -> 0 | J14: =G14*0.7 -> 0 | K14: =J14+I14+H14 -> 0 | L14: pcs | M14: 39169092 | N14: Kg
B15: KATEKUSU 3ø 30L | C15: 0.01 | D15: 0.8 | E15: 20000 | F15: =_xlfn.IFNA(VLOOKUP(B15,'PACKING LIST'!$B$35:$F$54,5,FALSE),0) -> 0 | G15: =ROUNDUP(F15/E15,0) -> 0 | H15: =F15*D15/1000 -> 0 | J15: =G15*0.7 -> 0 | K15: =J15+I15+H15 -> 0 | L15: pcs | M15: 39169092 | N15: Kg
B16: KATEKUSU 3ø 40L | C16: 0.01 | D16: 0.8 | E16: 20000 | F16: =_xlfn.IFNA(VLOOKUP(B16,'PACKING LIST'!$B$35:$F$54,5,FALSE),0) -> 0 | G16: =ROUNDUP(F16/E16,0) -> 0 | H16: =F16*D16/1000 -> 0 | J16: =G16*0.7 -> 0 | K16: =J16+I16+H16 -> 0 | L16: pcs | M16: 39169092 | N16: Kg
B17: KATEKUSU 3ø 45L | C17: 0.01 | D17: 0.8 | E17: 20000 | F17: =_xlfn.IFNA(VLOOKUP(B17,'PACKING LIST'!$B$35:$F$54,5,FALSE),0) -> 0 | G17: =ROUNDUP(F17/E17,0) -> 0 | H17: =F17*D17/1000 -> 0 | J17: =G17*0.7 -> 0 | K17: =J17+I17+H17 -> 0 | L17: pcs | M17: 39169092 | N17: Kg
B18: KATEKUSU 3ø 90L | C18: 0.013 | D18: 0.8 | E18: 20000 | F18: =_xlfn.IFNA(VLOOKUP(B18,'PACKING LIST'!$B$35:$F$54,5,FALSE),0) -> 0 | G18: =ROUNDUP(F18/E18,0) -> 0 | H18: =F18*D18/1000 -> 0 | J18: =G18*0.7 -> 0 | K18: =J18+I18+H18 -> 0 | L18: pcs | M18: 39169092 | N18: Kg
A19: =A13+1 -> 10 | B19: KATEKUSU 3ø 100L | C19: 0.013 | D19: 0.8 | E19: 20000 | F19: =_xlfn.IFNA(VLOOKUP(B19,'PACKING LIST'!$B$35:$F$54,5,FALSE),0) -> 0 | G19: =ROUNDUP(F19/E19,0) -> 0 | H19: =F19*D19/1000 -> 0 | J19: =G19*0.7 -> 0 | K19: =J19+I19+H19 -> 0 | L19: pcs | M19: 39169092 | N19: Kg
A20: =A19+1 -> 11 | B20: KATEKUSU 3ø 150L | C20: 0.013 | D20: 1.1 | E20: 10000 | F20: =_xlfn.IFNA(VLOOKUP(B20,'PACKING LIST'!$B$35:$F$54,5,FALSE),0) -> 0 | G20: =ROUNDUP(F20/E20,0) -> 0 | H20: =F20*D20/1000 -> 0 | J20: =G20*0.7 -> 0 | K20: =J20+I20+H20 -> 0 | L20: pcs | M20: 39169092 | N20: Kg
A21: =A19+1 -> 11 | B21: KATEKUSU 4ø 50L | C21: 0.013 | D21: 1.1 | E21: 10000 | F21: =_xlfn.IFNA(VLOOKUP(B21,'PACKING LIST'!$B$35:$F$54,5,FALSE),0) -> 0 | G21: =ROUNDUP(F21/E21,0) -> 0 | H21: =F21*D21/1000 -> 0 | J21: =G21*0.7 -> 0 | K21: =J21+I21+H21 -> 0 | L21: pcs | M21: 39169092 | N21: Kg
A22: =A20+1 -> 12 | B22: KATEKUSU 4ø 100L | C22: 0.016 | D22: 1.1 | E22: 10000 | F22: =_xlfn.IFNA(VLOOKUP(B22,'PACKING LIST'!$B$35:$F$54,5,FALSE),0) -> 0 | G22: =ROUNDUP(F22/E22,0) -> 0 | H22: =F22*D22/1000 -> 0 | J22: =G22*0.7 -> 0 | K22: =J22+I22+H22 -> 0 | L22: pcs | M22: 39169092 | N22: Kg
A23: =A22+1 -> 13 | B23: KATEKUSU 5ø 183L | C23: 0.053 | D23: 3.7 | E23: 5000 | F23: =_xlfn.IFNA(VLOOKUP(B23,'PACKING LIST'!$B$35:$F$54,5,FALSE),0) -> 0 | G23: =ROUNDUP(F23/E23,0) -> 0 | H23: =F23*D23/1000 -> 0 | J23: =G23*0.7 -> 0 | K23: =J23+I23+H23 -> 0 | L23: pcs | M23: 39169092 | N23: Kg
A24: =A23+1 -> 14 | B24: SHEET JOINT 100L | C24: 0.037 | D24: 4.3 | E24: 3000 | F24: =_xlfn.IFNA(VLOOKUP(B24,'PACKING LIST'!$B$35:$F$54,5,FALSE),0) -> 0 | G24: =ROUNDUP(F24/E24,0) -> 0 | H24: =F24*D24/1000 -> 0 | J24: =G24*0.7 -> 0 | K24: =J24+I24+H24 -> 0 | L24: pcs | M24: 39269049 | N24: PCE
A25: =A24+1 -> 15 | B25: SHEET JOINT 150L | C25: 0.05 | D25: 5.5 | E25: 1500 | F25: =_xlfn.IFNA(VLOOKUP(B25,'PACKING LIST'!$B$35:$F$54,5,FALSE),0) -> 0 | G25: =ROUNDUP(F25/E25,0) -> 0 | H25: =F25*D25/1000 -> 0 | J25: =G25*0.7 -> 0 | K25: =J25+I25+H25 -> 0 | L25: pcs | M25: 39269049 | N25: PCE
A26: =A25+1 -> 16 | B26: SHEET JOINT 200L | C26: 0.07 | D26: 7.2 | E26: 1500 | F26: =_xlfn.IFNA(VLOOKUP(B26,'PACKING LIST'!$B$35:$F$54,5,FALSE),0) -> 0 | G26: =ROUNDUP(F26/E26,0) -> 0 | H26: =F26*D26/1000 -> 0 | J26: =G26*0.7 -> 0 | K26: =J26+I26+H26 -> 0 | L26: pcs | M26: 39269049 | N26: PCE
A27: =A26+1 -> 17 | B27: SHEET JOINT 290L | C27: 0.08 | D27: 12.4 | E27: 1000 | F27: =_xlfn.IFNA(VLOOKUP(B27,'PACKING LIST'!$B$35:$F$54,5,FALSE),0) -> 0 | G27: =ROUNDUP(F27/E27,0) -> 0 | H27: =F27*D27/1000 -> 0 | J27: =G27*0.7 -> 0 | K27: =J27+I27+H27 -> 0 | L27: pcs | M27: 39269049 | N27: PCE
A28: =A27+1 -> 18 | B28: TABLE EDGE MI3 | C28: 0.587 | D28: 8.4 | E28: 50 | F28: =_xlfn.IFNA(VLOOKUP(B28,'PACKING LIST'!$B$35:$F$54,5,FALSE),0) -> 0 | G28: =ROUNDUP(F28/E28,0) -> 0 | H28: =F28*D28 -> 0 | J28: =G28*0 -> 0 | K28: =J28+I28+H28 -> 0 | L28: m | M28: 39169092 | N28: Kg
A29: =A28+1 -> 19 | B29: TABLE EDGE MI3 156 | C29: 2.875 | D29: =4140*167/1000 -> 691.38 | E29: 30 | F29: =_xlfn.IFNA(VLOOKUP(B29,'PACKING LIST'!$B$35:$F$54,5,FALSE),0) -> 240 | G29: =ROUNDUP(F29/E29,0) -> 8 | H29: =F29*D29 -> 165931.2 | J29: =G29*1 -> 8 | K29: =J29+I29+H29 -> 165939.2 | L29: pcs | M29: 39169092 | N29: Kg
A30: =A29+1 -> 20 | B30: TABLE EDGE MI3 26 | C30: 3.017 | D30: =4416*167/1000 -> 737.472 | E30: 30 | F30: =_xlfn.IFNA(VLOOKUP(B30,'PACKING LIST'!$B$35:$F$54,5,FALSE),0) -> 0 | G30: =ROUNDUP(F30/E30,0) -> 0 | H30: =F30*D30 -> 0 | J30: =G30*1 -> 0 | K30: =J30+I30+H30 -> 0 | L30: pcs | M30: 39169092 | N30: Kg
A31: =A30+1 -> 21 | B31: TABLE EDGE MI3 256 | C31: 3.229 | D31: =0.77*1000 -> 770 | E31: 30 | F31: =_xlfn.IFNA(VLOOKUP(B31,'PACKING LIST'!$B$35:$F$54,5,FALSE),0) -> 0 | G31: =ROUNDUP(F31/E31,0) -> 0 | H31: =F31*D31 -> 0 | J31: =G31*1 -> 0 | K31: =J31+I31+H31 -> 0 | L31: pcs | M31: 39169092 | N31: Kg
A32: =A31+1 -> 22 | B32: TABLE EDGE MI3 36 | C32: 3.158 | D32: =0.84*1000 -> 840 | E32: 30 | F32: =_xlfn.IFNA(VLOOKUP(B32,'PACKING LIST'!$B$35:$F$54,5,FALSE),0) -> 0 | G32: =ROUNDUP(F32/E32,0) -> 0 | H32: =F32*D32 -> 0 | J32: =G32*1 -> 0 | K32: =J32+I32+H32 -> 0 | L32: pcs | M32: 39169092 | N32: Kg
A33: =A32+1 -> 23 | B33: TABLE EDGE MI3 155 | C33: 2.509 | D33: =0.624*1000 -> 624 | E33: 30 | F33: =_xlfn.IFNA(VLOOKUP(B33,'PACKING LIST'!$B$35:$F$54,5,FALSE),0) -> 0 | G33: =ROUNDUP(F33/E33,0) -> 0 | H33: =F33*D33 -> 0 | J33: =G33*1 -> 0 | K33: =J33+I33+H33 -> 0 | L33: pcs | M33: 39169092 | N33: Kg
A34: =A33+1 -> 24 | B34: TABLE EDGE MI3 25 | C34: 2.698 | D34: =0.673*1000 -> 673 | E34: 30 | F34: =_xlfn.IFNA(VLOOKUP(B34,'PACKING LIST'!$B$35:$F$54,5,FALSE),0) -> 0 | G34: =ROUNDUP(F34/E34,0) -> 0 | H34: =F34*D34 -> 0 | J34: =G34*1 -> 0 | K34: =J34+I34+H34 -> 0 | L34: pcs | M34: 39169092 | N34: Kg
A35: =A34+1 -> 25 | B35: PUROTEKUTA 55788-02270 | C35: 0.2046 | D35: 21.6 | E35: 500 | F35: =_xlfn.IFNA(VLOOKUP(B35,'PACKING LIST'!$B$35:$F$54,5,FALSE),0) -> 0 | G35: =ROUNDUP(F35/E35,0) -> 0 | H35: =F35*D35/1000 -> 0 | J35: =G35*1 -> 0 | K35: =J35+I35+H35 -> 0 | L35: pcs | M35: 39169092 | N35: Kg
A36: =A35+1 -> 26 | B36: PUROTEKUTA 1422L (55788-42050) | C36: 0.234 | D36: 24 | E36: 500 | F36: =_xlfn.IFNA(VLOOKUP(B36,'PACKING LIST'!$B$35:$F$54,5,FALSE),0) -> 0 | G36: =ROUNDUP(F36/E36,0) -> 0 | H36: =F36*D36/1000 -> 0 | J36: =G36*1 -> 0 | K36: =J36+I36+H36 -> 0 | L36: pcs | M36: 39169092 | N36: Kg | P36: =263636+165000 -> 428636
B37: PUROTEKUTA 55788-TOA0010 | C37: 0.224 | D37: 24 | E37: 500 | F37: =_xlfn.IFNA(VLOOKUP(B37,'PACKING LIST'!$B$35:$F$54,5,FALSE),0) -> 0 | G37: =ROUNDUP(F37/E37,0) -> 0 | H37: =F37*D37/1000 -> 0 | J37: =G37*1 -> 0 | K37: =J37+I37+H37 -> 0 | L37: pcs | M37: 39169092 | N37: Kg
B38: PUROTEKUTA 55788-TOA020 | C38: 0.224 | D38: 24 | E38: 500 | F38: =_xlfn.IFNA(VLOOKUP(B38,'PACKING LIST'!$B$35:$F$54,5,FALSE),0) -> 0 | G38: =ROUNDUP(F38/E38,0) -> 0 | H38: =F38*D38/1000 -> 0 | J38: =G38*1 -> 0 | K38: =J38+I38+H38 -> 0 | L38: pcs | M38: 39169092 | N38: Kg
A39: =A36+1 -> 27 | B39: PUROTEKUTA 1383L OK100 | C39: 0.228 | D39: 21.7 | E39: 500 | F39: =_xlfn.IFNA(VLOOKUP(B39,'PACKING LIST'!$B$35:$F$54,5,FALSE),0) -> 0 | G39: =ROUNDUP(F39/E39,0) -> 0 | H39: =F39*D39/1000 -> 0 | J39: =G39*1 -> 0 | K39: =J39+I39+H39 -> 0 | L39: pcs | M39: 39169092 | N39: Kg
A40: =A39+1 -> 28 | B40: PUROTEKUTA 2A4P1-018G | C40: 0.229 | D40: 22.1 | E40: 500 | F40: =_xlfn.IFNA(VLOOKUP(B40,'PACKING LIST'!$B$35:$F$54,5,FALSE),0) -> 0 | G40: =ROUNDUP(F40/E40,0) -> 0 | H40: =F40*D40/1000 -> 0 | J40: =G40*1 -> 0 | K40: =J40+I40+H40 -> 0 | L40: pcs | M40: 39169092 | N40: Kg
A41: =A40+1 -> 29 | B41: PUROTEKUTA 55788-48080 | C41: 0.251 | D41: 25 | E41: 500 | F41: =_xlfn.IFNA(VLOOKUP(B41,'PACKING LIST'!$B$35:$F$54,5,FALSE),0) -> 0 | G41: =ROUNDUP(F41/E41,0) -> 0 | H41: =F41*D41/1000 -> 0 | J41: =G41*1 -> 0 | K41: =J41+I41+H41 -> 0 | L41: pcs | M41: 39169092 | N41: Kg
A42: =A41+1 -> 30 | B42: PUROTEKUTA 55788-48090 | C42: 0.251 | D42: 25 | E42: 500 | F42: =_xlfn.IFNA(VLOOKUP(B42,'PACKING LIST'!$B$35:$F$54,5,FALSE),0) -> 9000 | G42: =ROUNDUP(F42/E42,0) -> 18 | H42: =F42*D42/1000 -> 225 | J42: =G42*1 -> 18 | K42: =J42+I42+H42 -> 243 | L42: pcs | M42: 39169092 | N42: Kg
A43: =A41+1 -> 30 | B43: PUROTEKUTA 55788-K0060 | C43: 0.224 | D43: 23 | E43: 500 | F43: =_xlfn.IFNA(VLOOKUP(B43,'PACKING LIST'!$B$35:$F$54,5,FALSE),0) -> 5500 | G43: =ROUNDUP(F43/E43,0) -> 11 | H43: =F43*D43/1000 -> 126.5 | J43: =G43*1 -> 11 | K43: =J43+I43+H43 -> 137.5 | L43: pcs | M43: 39169092 | N43: Kg
A44: =A43+1 -> 31 | B44: PUROTEKUTA 55788-60080 | C44: 0.233 | D44: 22.8 | E44: 500 | F44: =_xlfn.IFNA(VLOOKUP(B44,'PACKING LIST'!$B$35:$F$54,5,FALSE),0) -> 0 | G44: =ROUNDUP(F44/E44,0) -> 0 | H44: =F44*D44/1000 -> 0 | J44: =G44*1 -> 0 | K44: =J44+I44+H44 -> 0 | L44: pcs | M44: 39169092 | N44: Kg
A45: =A44+1 -> 32 | B45: PUROTEKUTA 2A4P1-022G | C45: 0.235 | D45: 23.5 | E45: 500 | F45: =_xlfn.IFNA(VLOOKUP(B45,'PACKING LIST'!$B$35:$F$54,5,FALSE),0) -> 11000 | G45: =ROUNDUP(F45/E45,0) -> 22 | H45: =F45*D45/1000 -> 258.5 | J45: =G45*1 -> 22 | K45: =J45+I45+H45 -> 280.5 | L45: pcs | M45: 39169092 | N45: Kg
B46: PUROTEKUTA 55788-60110 | C46: 0.223 | D46: 25 | E46: 500 | F46: =_xlfn.IFNA(VLOOKUP(B46,'PACKING LIST'!$B$35:$F$54,5,FALSE),0) -> 13000 | G46: =ROUNDUP(F46/E46,0) -> 26 | H46: =F46*D46/1000 -> 325 | J46: =G46*1 -> 26 | K46: =J46+I46+H46 -> 351 | L46: pcs | M46: 39169092 | N46: Kg
B47: PUROTEKUTA 55788-16110 | C47: 0.223 | D47: 25 | E47: 500 | F47: =_xlfn.IFNA(VLOOKUP(B47,'PACKING LIST'!$B$35:$F$54,5,FALSE),0) -> 11000 | G47: =ROUNDUP(F47/E47,0) -> 22 | H47: =F47*D47/1000 -> 275 | J47: =G47*1 -> 22 | K47: =J47+I47+H47 -> 297 | L47: pcs | M47: 39169092 | N47: Kg
B48: PUROTEKUTA 55788-52350 | C48: 0.213 | D48: 23.5 | E48: 500 | F48: =_xlfn.IFNA(VLOOKUP(B48,'PACKING LIST'!$B$35:$F$54,5,FALSE),0) -> 6000 | G48: =ROUNDUP(F48/E48,0) -> 12 | H48: =F48*D48/1000 -> 141 | J48: =G48*1 -> 12 | L48: pcs | M48: 39169092 | N48: Kg
B49: PUROTEKUTA 55788-52360 | C49: 0.223 | D49: 25 | E49: 500 | F49: =_xlfn.IFNA(VLOOKUP(B49,'PACKING LIST'!$B$35:$F$54,5,FALSE),0) -> 5000 | G49: =ROUNDUP(F49/E49,0) -> 10 | H49: =F49*D49/1000 -> 125 | J49: =G49*1 -> 10 | L49: pcs | M49: 39169092 | N49: Kg
A50: =A45+1 -> 33 | B50: DIP TUBE | C50: 1.22 | D50: 52 | E50: 100 | F50: =_xlfn.IFNA(VLOOKUP(B50,'PACKING LIST'!$B$35:$F$54,5,FALSE),0) -> 0 | G50: =ROUNDUP(F50/E50,0) -> 0 | H50: =F50*D50/1000 -> 0 | J50: =G50*1 -> 0 | K50: =J50+I50+H50 -> 0 | L50: pcs | M50: 39172100 | N50: PCE | P50: Debuchubu
A51: =A50+1 -> 34 | B51: PLASTIC TUBE | C51: 4.8 | D51: 0.5 | E51: 20 | F51: =_xlfn.IFNA(VLOOKUP(B51,'PACKING LIST'!$B$35:$F$54,5,FALSE),0) -> 0 | G51: =ROUNDUP(F51/E51,0) -> 0 | H51: =F51*D51/1000 -> 0 | J51: =G51*1 -> 0 | K51: =J51+I51+H51 -> 0 | L51: pcs | M51: 39172929 | N51: PCE
A52: =A55+1 -> 36 | B52: COVER SIDE TRIM | C52: 0.955 | D52: 72 | E52: 200 | F52: =_xlfn.IFNA(VLOOKUP(B52,'PACKING LIST'!$B$35:$F$54,5,FALSE),0) -> 0 | G52: =ROUNDUP(F52/E52,0) -> 0 | H52: =F52*D52/1000 -> 0 | J52: =G52*1 -> 0 | K52: =J52+I52+H52 -> 0 | L52: pcs | M52: 39169092 | N52: Kg
B53: PILLOW | C53: 30.35 | D53: 1500 | E53: 1 | F53: =_xlfn.IFNA(VLOOKUP(B53,'PACKING LIST'!$B$35:$F$54,5,FALSE),0) -> 0 | G53: =ROUNDUP(F53/E53,0) -> 0 | H53: =F53*D53/1000 -> 0 | J53: =G53*0.5 -> 0 | L53: set
B54: GỐI XÁM | C54: 31.5 | E54: 1 | F54: =_xlfn.IFNA(VLOOKUP(B54,'PACKING LIST'!$B$35:$F$54,5,FALSE),0) -> 0 | H54: =F54*D54/1000 -> 0 | J54: =G54*1 -> 0 | L54: set
A55: =A51+1 -> 35 | B55: MASK | C55: 0.24 | E55: 400 | F55: =_xlfn.IFNA(VLOOKUP(B55,'PACKING LIST'!$B$35:$F$54,5,FALSE),0) -> 0 | G55: =ROUNDUP(F55/E55,0) -> 0 | H55: =F55*D55/1000 -> 0 | J55: =G55*1 -> 0 | K55: =J55+I55+H55 -> 0 | L55: pcs | M55: 63079090 | N55: PCE
B56: MASUKU | C56: 0.26 | D56: 18.3 | E56: 400 | F56: =_xlfn.IFNA(VLOOKUP(B56,'PACKING LIST'!$B$35:$F$54,5,FALSE),0) -> 0 | G56: =ROUNDUP(F56/E56,0) -> 0 | H56: =F56*D56/1000 -> 0 | J56: =G56*1 -> 0 | K56: =J56+I56+H56 -> 0 | L56: bag | M56: 63079090 | N56: PCE | P56: 34046
A57: =A52+1 -> 37 | B57: MASUKU SMALL | C57: 0.25 | D57: 16.3 | E57: 400 | F57: =_xlfn.IFNA(VLOOKUP(B57,'PACKING LIST'!$B$35:$F$54,5,FALSE),0) -> 0 | G57: =ROUNDUP(F57/E57,0) -> 0 | H57: =F57*D57/1000 -> 0 | J57: =G57*1 -> 0 | K57: =J57+I57+H57 -> 0 | L57: bag | M57: 63079090 | N57: PCE | P57: 34080
B58: MASK 42811 | C58: 0.2 | D58: 83.3 | E58: 120 | L58: bag
A59: =A57+1 -> 38 | B59: MASK 515220 | C59: 0.47 | D59: 34.6 | E59: 240 | F59: =_xlfn.IFNA(VLOOKUP(B59,'PACKING LIST'!$B$35:$F$54,5,FALSE),0) -> 0 | G59: =ROUNDUP(F59/E59,0) -> 0 | H59: =F59*D59/1000 -> 0 | J59: =G59*1 -> 0 | K59: =J59+I59+H59 -> 0 | L59: bag | M59: 63079090 | N59: PCE | P59: 9.8/thung
A60: =A59+1 -> 39 | B60: MASK 515222 | C60: 0.46 | D60: 28.3 | E60: 240 | F60: =_xlfn.IFNA(VLOOKUP(B60,'PACKING LIST'!$B$35:$F$54,5,FALSE),0) -> 0 | G60: =ROUNDUP(F60/E60,0) -> 0 | H60: =F60*D60/1000 -> 0 | J60: =G60*1 -> 0 | K60: =J60+I60+H60 -> 0 | L60: bag | M60: 63079090 | N60: PCE | P60: 8.2/thung
B61: MASK 515221 | C61: 0.261 | D61: =132.5 -> 132.5 | E61: 40 | F61: =_xlfn.IFNA(VLOOKUP(B61,'PACKING LIST'!$B$35:$F$54,5,FALSE),0) -> 0 | G61: =ROUNDUP(F61/E61,0) -> 0 | H61: =F61*D61/1000 -> 0 | J61: =G61*1 -> 0 | K61: =J61+I61+H61 -> 0 | L61: bag | M61: 63079090 | N61: PCE | P61: 6kg
B62: MASK 515223 | C62: 1.7 | D62: 107.5 | E62: 40 | F62: =_xlfn.IFNA(VLOOKUP(B62,'PACKING LIST'!$B$35:$F$54,5,FALSE),0) -> 0 | G62: =ROUNDUP(F62/E62,0) -> 0 | H62: =F62*D62/1000 -> 0 | J62: =G62*1 -> 0 | K62: =J62+I62+H62 -> 0 | L62: bag | M62: 63079090 | N62: PCE | P62: 5kg
A63: =A60+1 -> 40 | B63: MASK 515530 | C63: 1.51 | D63: 40 | E63: 200 | F63: =_xlfn.IFNA(VLOOKUP(B63,'PACKING LIST'!$B$35:$F$54,5,FALSE),0) -> 0 | G63: =ROUNDUP(F63/E63,0) -> 0 | H63: =F63*D63/1000 -> 0 | J63: =G63*1 -> 0 | K63: =J63+I63+H63 -> 0 | L63: bag | M63: 63079090 | N63: PCE | P63: 2.9kg
A64: =A63+1 -> 41 | B64: MASK 515531 | C64: 1.47 | D64: 35 | E64: 200 bag/Box | F64: =_xlfn.IFNA(VLOOKUP(B64,'PACKING LIST'!$B$35:$F$54,5,FALSE),0) -> 0 | G64: =ROUNDUP(F64/E64,0) -> #VALUE! | H64: =F64*D64/1000 -> 0 | J64: =G64*1 -> #VALUE! | K64: =J64+I64+H64 -> #VALUE! | L64: bag | M64: 63079090 | N64: PCE | P64: 2.4kg
B65: MASK 34927 | C65: 0.62 | D65: 50 | E65: 200 | H65: =F65*D65/1000 -> 0 | L65: bag | M65: 63079090 | N65: PCE | P65: 11.5kg/thung
B66: MASK 34928 | C66: 0.59 | D66: 40 | E66: 200 | H66: =F66*D66/1000 -> 0 | L66: bag | M66: 63079090 | N66: PCE | P66: 9.7kg/thung
B67: MASK 34929 | C67: 0.62 | D67: 50 | E67: 200 | H67: =F67*D67/1000 -> 0 | L67: bag | M67: 63079090 | N67: PCE | P67: 11kg/thung
B68: MASK 34930 | C68: 0.59 | D68: 40 | E68: 200 | H68: =F68*D68/1000 -> 0 | L68: bag | M68: 63079090 | N68: PCE | P68: 9.7kg/thung
A69: =A64+1 -> 42 | B69: MASK 34931 | C69: 0.26 | D69: 50 | E69: 400 | F69: =_xlfn.IFNA(VLOOKUP(B69,'PACKING LIST'!$B$35:$F$54,5,FALSE),0) -> 0 | G69: =ROUNDUP(F69/E69,0) -> 0 | H69: =F69*D69/1000 -> 0 | J69: =G69*1 -> 0 | K69: =J69+I69+H69 -> 0 | L69: bag | M69: 63079090 | N69: PCE
A70: =A69+1 -> 43 | B70: MASK 34933 | C70: 0.26 | D70: 40 | E70: 400 | F70: =_xlfn.IFNA(VLOOKUP(B70,'PACKING LIST'!$B$35:$F$54,5,FALSE),0) -> 0 | G70: =ROUNDUP(F70/E70,0) -> 0 | H70: =F70*D70/1000 -> 0 | J70: =G70*1 -> 0 | K70: =J70+I70+H70 -> 0 | L70: bag | M70: 63079090 | N70: PCE
A71: =A70+1 -> 44 | B71: GENTLE EAR NON-WOVEN MASK REGULAR | C71: 0.62 | D71: 50 | E71: 200 | F71: =_xlfn.IFNA(VLOOKUP(B71,'PACKING LIST'!$B$35:$F$54,5,FALSE),0) -> 0 | G71: 1 | H71: =F71*D71/1000 -> 0 | J71: =G71*1 -> 1 | K71: =J71+I71+H71 -> 1 | L71: bag | M71: 63079090 | N71: PCE | P71: 9.4/hung
A72: =A71+1 -> 45 | B72: GENTLE EAR NON-WOVEN MASK SMALL | C72: 0.59 | D72: 40 | E72: 200 | F72: =_xlfn.IFNA(VLOOKUP(B72,'PACKING LIST'!$B$35:$F$54,5,FALSE),0) -> 0 | G72: =ROUNDUP(F72/E72,0) -> 0 | H72: =F72*D72/1000 -> 0 | J72: =G72*1 -> 0 | K72: =J72+I72+H72 -> 0 | L72: bag | M72: 63079090 | N72: PCE | P72: 8.3/thung
A73: =A72+1 -> 46 | B73: MASK KOSOU FUKURO | C73: 0.105 | D73: 5.85 | E73: 1 | F73: =_xlfn.IFNA(VLOOKUP(B73,'PACKING LIST'!$B$35:$F$54,5,FALSE),0) -> 0 | G73: =ROUNDUP(F73/E73,0) -> 0 | H73: =F73*D73/1000 -> 0 | J73: 3 | K73: =J73+I73+H73 -> 3 | L73: bag | M73: 63079090 | N73: PCE
A74: =A73+1 -> 47 | B74: MASK KOSOU FUKURO LILAC | C74: 0.105 | D74: 5.85 | E74: 1 | F74: =_xlfn.IFNA(VLOOKUP(B74,'PACKING LIST'!$B$35:$F$54,5,FALSE),0) -> 0 | G74: =ROUNDUP(F74/E74,0) -> 0 | H74: =F74*D74/1000 -> 0 | J74: 1 | K74: =J74+I74+H74 -> 1 | L74: bag | M74: 63079090 | N74: PCE
B75: MASK KOSOU FUKURO PINK | C75: 0.105 | D75: 5.85 | E75: 1 | F75: =_xlfn.IFNA(VLOOKUP(B75,'PACKING LIST'!$B$35:$F$54,5,FALSE),0) -> 0 | G75: =ROUNDUP(F75/E75,0) -> 0 | H75: =F75*D75/1000 -> 0 | J75: 1 | K75: =J75+I75+H75 -> 1 | L75: bag
B76: MASK KOSOU FUKURO GRAY | C76: 0.105 | D76: 5.85 | E76: 1 | F76: =_xlfn.IFNA(VLOOKUP(B76,'PACKING LIST'!$B$35:$F$54,5,FALSE),0) -> 0 | G76: =ROUNDUP(F76/E76,0) -> 0 | H76: =F76*D76/1000 -> 0 | J76: 1 | K76: =J76+I76+H76 -> 1 | L76: bag
B77: MASK KOSOU FUKURO LIGHT GRAY | C77: 0.105 | D77: 5.85 | E77: 1 | F77: =_xlfn.IFNA(VLOOKUP(B77,'PACKING LIST'!$B$35:$F$54,5,FALSE),0) -> 0 | G77: =ROUNDUP(F77/E77,0) -> 0 | H77: =F77*D77/1000 -> 0 | J77: 1 | K77: =J77+I77+H77 -> 1 | L77: bag
B78: MASK KOSOU FUKURO BEIGE | C78: 0.105 | D78: 5.85 | E78: 1 | F78: =_xlfn.IFNA(VLOOKUP(B78,'PACKING LIST'!$B$35:$F$54,5,FALSE),0) -> 0 | G78: =ROUNDUP(F78/E78,0) -> 0 | H78: =F78*D78/1000 -> 0 | J78: 1 | K78: =J78+I78+H78 -> 1 | L78: bag
A79: =A74+1 -> 48 | B79: Mask C01036 White | C79: 0.42 | D79: 25 | E79: 240 | F79: =_xlfn.IFNA(VLOOKUP(B79,'[3]PACKING LIST'!$B$35:$E$48,4,FALSE),0) -> 0 | G79: =ROUNDUP(F79/E79,0) -> 0 | H79: =F79*D79/1000 -> 0 | J79: =G79*1.4 -> 0 | K79: =J79+I79+H79 -> 0 | L79: bag | M79: 63079090 | N79: PCE | P79: 6.9kg
A80: =A79+1 -> 49 | B80: Mask C01036 Light gray | C80: 0.42 | D80: 24.5 | E80: 240 | F80: =_xlfn.IFNA(VLOOKUP(B80,'[3]PACKING LIST'!$B$35:$E$48,4,FALSE),0) -> 0 | G80: =ROUNDUP(F80/E80,0) -> 0 | H80: =F80*D80/1000 -> 0 | J80: =G80*1.4 -> 0 | K80: =J80+I80+H80 -> 0 | L80: bag | M80: 63079090 | N80: PCE
A81: =A80+1 -> 50 | B81: Mask C01036 Gray | C81: 0.42 | D81: 24.5 | E81: 240 | F81: =_xlfn.IFNA(VLOOKUP(B81,'[3]PACKING LIST'!$B$35:$E$48,4,FALSE),0) -> 0 | G81: =ROUNDUP(F81/E81,0) -> 0 | H81: =F81*D81/1000 -> 0 | J81: =G81*1.4 -> 0 | K81: =J81+I81+H81 -> 0 | L81: bag | M81: 63079090 | N81: PCE
A82: =A81+1 -> 51 | B82: Mask C01036 Beige | C82: 0.42 | D82: 24.5 | E82: 240 | F82: =_xlfn.IFNA(VLOOKUP(B82,'[3]PACKING LIST'!$B$35:$E$48,4,FALSE),0) -> 0 | G82: =ROUNDUP(F82/E82,0) -> 0 | H82: =F82*D82/1000 -> 0 | J82: =G82*1.4 -> 0 | K82: =J82+I82+H82 -> 0 | L82: bag | M82: 63079090 | N82: PCE
A83: =A82+1 -> 52 | B83: Mask C01036 Pink | C83: 0.42 | D83: 24.5 | E83: 240 | F83: =_xlfn.IFNA(VLOOKUP(B83,'[3]PACKING LIST'!$B$35:$E$48,4,FALSE),0) -> 0 | G83: =ROUNDUP(F83/E83,0) -> 0 | H83: =F83*D83/1000 -> 0 | J83: =G83*1.4 -> 0 | K83: =J83+I83+H83 -> 0 | L83: bag | M83: 63079090 | N83: PCE
A84: =A83+1 -> 53 | B84: Mask C01036 Lilac | C84: 0.42 | D84: 24.5 | E84: 240 | F84: =_xlfn.IFNA(VLOOKUP(B84,'[3]PACKING LIST'!$B$35:$E$48,4,FALSE),0) -> 0 | G84: =ROUNDUP(F84/E84,0) -> 0 | H84: =F84*D84/1000 -> 0 | J84: =G84*1.4 -> 0 | K84: =J84+I84+H84 -> 0 | L84: bag | M84: 63079090 | N84: PCE
A85: =A84+1 -> 54 | B85: Mask C01038 White | C85: 0.41 | D85: 20.5 | E85: 240 | F85: =_xlfn.IFNA(VLOOKUP(B85,'[3]PACKING LIST'!$B$35:$E$48,4,FALSE),0) -> 0 | G85: =ROUNDUP(F85/E85,0) -> 0 | H85: =F85*D85/1000 -> 0 | J85: =G85*1.4 -> 0 | K85: =J85+I85+H85 -> 0 | L85: bag | M85: 63079090 | N85: PCE
A86: =A85+1 -> 55 | B86: Mask C01037 White | C86: 1.61 | D86: 135 | E86: 40bag/box | F86: =_xlfn.IFNA(VLOOKUP(B86,'[3]PACKING LIST'!$B$35:$E$48,4,FALSE),0) -> 3920 | G86: =ROUNDUP(F86/E86,0) -> #VALUE! | H86: =F86*D86/1000 -> 529.2 | J86: =G86*1.4 -> #VALUE! | K86: =J86+I86+H86 -> #VALUE! | L86: bag | M86: 63079090 | N86: PCE | P86: 6kg
A87: =A86+1 -> 56 | B87: Mask C01037 Light gray | C87: 1.61 | D87: 135 | E87: 40bag/box | F87: =_xlfn.IFNA(VLOOKUP(B87,'[3]PACKING LIST'!$B$35:$E$48,4,FALSE),0) -> 4000 | G87: =ROUNDUP(F87/E87,0) -> #VALUE! | H87: =F87*D87/1000 -> 540 | J87: =G87*1.4 -> #VALUE! | K87: =J87+I87+H87 -> #VALUE! | L87: bag | M87: 63079090 | N87: PCE
A88: =A87+1 -> 57 | B88: Mask C01037 Gray | C88: 1.61 | D88: 135 | E88: 40bag/box | F88: =_xlfn.IFNA(VLOOKUP(B88,'[3]PACKING LIST'!$B$35:$E$48,4,FALSE),0) -> 0 | G88: =ROUNDUP(F88/E88,0) -> #VALUE! | H88: =F88*D88/1000 -> 0 | J88: =G88*1.4 -> #VALUE! | K88: =J88+I88+H88 -> #VALUE! | L88: bag | M88: 63079090 | N88: PCE
A89: =A88+1 -> 58 | B89: Mask C01037 Beige | C89: 1.61 | D89: 135 | E89: 40bag/box | F89: =_xlfn.IFNA(VLOOKUP(B89,'[3]PACKING LIST'!$B$35:$E$48,4,FALSE),0) -> 5000 | G89: =ROUNDUP(F89/E89,0) -> #VALUE! | H89: =F89*D89/1000 -> 675 | J89: =G89*1.4 -> #VALUE! | K89: =J89+I89+H89 -> #VALUE! | L89: bag | M89: 63079090 | N89: PCE
A90: =A89+1 -> 59 | B90: Mask C01037 Pink | C90: 1.61 | D90: 135 | E90: 40bag/box | F90: =_xlfn.IFNA(VLOOKUP(B90,'[3]PACKING LIST'!$B$35:$E$48,4,FALSE),0) -> 5000 | G90: =ROUNDUP(F90/E90,0) -> #VALUE! | H90: =F90*D90/1000 -> 675 | J90: =G90*1.4 -> #VALUE! | K90: =J90+I90+H90 -> #VALUE! | L90: bag | M90: 63079090 | N90: PCE
A91: =A90+1 -> 60 | B91: Mask C01037 Lilac | C91: 1.61 | D91: 135 | E91: 40bag/box | F91: =_xlfn.IFNA(VLOOKUP(B91,'[3]PACKING LIST'!$B$35:$E$48,4,FALSE),0) -> 2000 | G91: =ROUNDUP(F91/E91,0) -> #VALUE! | H91: =F91*D91/1000 -> 270 | J91: =G91*1.4 -> #VALUE! | K91: =J91+I91+H91 -> #VALUE! | L91: bag | M91: 63079090 | N91: PCE
A92: =A91+1 -> 61 | B92: Mask C01039 White | C92: 1.55 | D92: 135 | E92: 40bag/box | F92: =_xlfn.IFNA(VLOOKUP(B92,'[3]PACKING LIST'!$B$35:$E$48,4,FALSE),0) -> 0 | G92: =ROUNDUP(F92/E92,0) -> #VALUE! | H92: =F92*D92/1000 -> 0 | J92: =G92*1.4 -> #VALUE! | K92: =J92+I92+H92 -> #VALUE! | L92: bag | M92: 63079090 | N92: PCE
A93: =A92+1 -> 62 | B93: Mask C01072 Stylist | C93: 1.61 | D93: 135 | E93: 40bag/box | F93: =_xlfn.IFNA(VLOOKUP(B93,'[3]PACKING LIST'!$B$35:$E$48,4,FALSE),0) -> 4000 | G93: =ROUNDUP(F93/E93,0) -> #VALUE! | H93: =F93*D93/1000 -> 540 | J93: =G93*1.4 -> #VALUE! | K93: =J93+I93+H93 -> #VALUE! | L93: bag | M93: 63079090 | N93: PCE
A94: =A93+1 -> 63 | B94: Mask C01074 Sweet | C94: 1.61 | D94: 135 | E94: 40bag/box | F94: =_xlfn.IFNA(VLOOKUP(B94,'[3]PACKING LIST'!$B$35:$E$48,4,FALSE),0) -> 3320 | G94: =ROUNDUP(F94/E94,0) -> #VALUE! | H94: =F94*D94/1000 -> 448.2 | J94: =G94*1.4 -> #VALUE! | K94: =J94+I94+H94 -> #VALUE! | L94: bag | M94: 63079090 | N94: PCE
A95: =A94+1 -> 64 | B95: Pallet (No Commerical Value) | C95: 5 | F95: =_xlfn.IFNA(VLOOKUP(B95,'[3]PACKING LIST'!$B$35:$E$48,4,FALSE),0) -> 0 | G95: =ROUNDUP(F95/E95,0) -> #DIV/0! | H95: =F95*D95/1000 -> 0 | J95: =G95*1.4 -> #DIV/0! | K95: =J95+I95+H95 -> #DIV/0! | L95: pcs
A96: =A95+1 -> 65 | B96: LDBA044800-8 DOOR CENTER SASH | C96: 28 | D96: 220 | E96: 6 | F96: =_xlfn.IFNA(VLOOKUP(B96,'[3]PACKING LIST'!$B$35:$E$48,4,FALSE),0) -> 0 | G96: =ROUNDUP(F96/E96,0) -> 0 | H96: =F96*D96/1000 -> 0 | J96: =G96*1.4 -> 0 | K96: =J96+I96+H96 -> 0 | L96: pcs | M96: 39269099 | N96: PCE
A97: =A96+1 -> 66 | B97: LDBA045100-8 DOOR CENTER SASH | C97: 28 | D97: 410 | F97: =_xlfn.IFNA(VLOOKUP(B97,'[3]PACKING LIST'!$B$35:$E$48,4,FALSE),0) -> 0 | G97: =ROUNDUP(F97/E97,0) -> #DIV/0! | H97: =F97*D97/1000 -> 0 | J97: =G97*1.4 -> #DIV/0! | K97: =J97+I97+H97 -> #DIV/0! | L97: pcs | M97: 39269099 | N97: PCE
B98: LDBA094401-0 FRAME BRAKER(TB)-803 | C98: =10 -> 10 | D98: 406 | G98: =ROUNDUP(F98/E98,0) -> #DIV/0! | H98: =F98*D98/1000 -> 0 | J98: =G98*1.4 -> #DIV/0! | K98: =J98+I98+H98 -> #DIV/0! | L98: pcs
B99: LDBA094402-0 FRAME BRAKER(RL)-803 | C99: =10 -> 10 | D99: 702 | G99: =ROUNDUP(F99/E99,0) -> #DIV/0! | H99: =F99*D99/1000 -> 0 | J99: =G99*1.4 -> #DIV/0! | K99: =J99+I99+H99 -> #DIV/0! | L99: pcs
B100: LDBA095001-0 DOOR GLASS SASH(TB)-803 | C100: =10 -> 10 | D100: 225 | G100: =ROUNDUP(F100/E100,0) -> #DIV/0! | H100: =F100*D100/1000 -> 0 | J100: =G100*1.4 -> #DIV/0! | K100: =J100+I100+H100 -> #DIV/0! | L100: pcs
B101: LDBA095002-0 DOOR GLASS SASH(RL)-803 | C101: =10 -> 10 | D101: 601 | G101: =ROUNDUP(F101/E101,0) -> #DIV/0! | H101: =F101*D101/1000 -> 0 | J101: =G101*1.4 -> #DIV/0! | K101: =J101+I101+H101 -> #DIV/0! | L101: pcs
...

Sheet dia chỉ
A2: FROM: MASUDA VINYL VIETNAM CO.,LTD
A4: LOT NO1 DONG VANG DINH TRAM INDUSTRIAL ZONE
A5: NENH WARD BAC NINH PROVINCE VIET NAM
A6: TEL : 0204 3662 777
A9: TO: MASUDA VINYL CO.,LTD
A11: 390ROKUGAIKECYOU KITAKU NAGOYA CITY AICHI JAPAN
A13: TEL : 052-901-9373
